Workbook

Sheet Budget - Topeka
B1: Topeka Self Storage
B2: Budget
B3: January - December 2026
B5: 46023 | C5: 46054 | D5: 46082 | E5: 46113 | F5: 46143 | G5: 46174 | H5: 46204 | I5: 46235 | J5: 46266 | K5: 46296 | L5: 46327 | M5: 46357
A6: Rented | B6: ='Budget - Grantville'!B6+'Budget - Tyler'!B6 -> 8 | C6: ='Budget - Grantville'!C6+'Budget - Tyler'!C6 -> 11 | D6: ='Budget - Grantville'!D6+'Budget - Tyler'!D6 -> 11 | E6: ='Budget - Grantville'!E6+'Budget - Tyler'!E6 -> 13 | F6: ='Budget - Grantville'!F6+'Budget - Tyler'!F6 -> 15 | G6: ='Budget - Grantville'!G6+'Budget - Tyler'!G6 -> 15 | H6: ='Budget - Grantville'!H6+'Budget - Tyler'!H6 -> 18 | I6: ='Budget - Grantville'!I6+'Budget - Tyler'!I6 -> 18 | ... M6: ='Budget - Grantville'!M6+'Budget - Tyler'!M6 -> 12
A7: Vacated | B7: ='Budget - Grantville'!B7+'Budget - Tyler'!B7 -> 10.56 | C7: ='Budget - Grantville'!C7+'Budget - Tyler'!C7 -> 12.32 | D7: ='Budget - Grantville'!D7+'Budget - Tyler'!D7 -> 12.2276 | E7: ='Budget - Grantville'!E7+'Budget - Tyler'!E7 -> 12.141668 | F7: ='Budget - Grantville'!F7+'Budget - Tyler'!F7 -> 12.201751 | G7: ='Budget - Grantville'!G7+'Budget - Tyler'!G7 -> 12.397629 | H7: ='Budget - Grantville'!H7+'Budget - Tyler'!H7 -> 12.579795 | I7: ='Budget - Grantville'!I7+'Budget - Tyler'!I7 -> 12.959209 | ... M7: ='Budget - Grantville'!M7+'Budget - Tyler'!M7 -> 11.927499
A8: Net occupied | B8: ='Budget - Grantville'!B8+'Budget - Tyler'!B8 -> 176 | C8: ='Budget - Grantville'!C8+'Budget - Tyler'!C8 -> 174.68 | D8: ='Budget - Grantville'!D8+'Budget - Tyler'!D8 -> 173.4524 | E8: ='Budget - Grantville'!E8+'Budget - Tyler'!E8 -> 174.31073 | F8: ='Budget - Grantville'!F8+'Budget - Tyler'!F8 -> 177.10898 | G8: ='Budget - Grantville'!G8+'Budget - Tyler'!G8 -> 179.71135 | H8: ='Budget - Grantville'!H8+'Budget - Tyler'!H8 -> 185.13156 | I8: ='Budget - Grantville'!I8+'Budget - Tyler'!I8 -> 190.17235 | ... M8: ='Budget - Grantville'!M8+'Budget - Tyler'!M8 -> 186.57776
A9: % occupied | B9: =B8/(126+82) -> 0.84615385 | C9: =C8/(126+82) -> 0.83980769 | D9: =D8/(126+82) -> 0.83390577 | E9: =E8/(126+82) -> 0.83803237 | F9: =F8/(126+82) -> 0.85148548 | G9: =G8/(126+82) -> 0.86399689 | H9: =H8/(126+82) -> 0.89005556 | I9: =I8/(126+82) -> 0.91429014 | ... M9: =M8/(126+82) -> 0.89700846 | O9: T12 Actual
B10: 46023 | C10: 46054 | D10: 46082 | E10: 46113 | F10: 46143 | G10: 46174 | H10: 46204 | I10: 46235 | J10: 46266 | K10: 46296 | L10: 46327 | M10: 46357 | N10: Total | O10: 10/1/2024 - 9/30/2025
A11: Revenue Projection
A12: Rent Income | B12: ='Budget - Grantville'!B12+'Budget - Tyler'!B12 -> 24737.009 | C12: ='Budget - Grantville'!C12+'Budget - Tyler'!C12 -> 24623.314 | D12: ='Budget - Grantville'!D12+'Budget - Tyler'!D12 -> 24517.577 | E12: ='Budget - Grantville'!E12+'Budget - Tyler'!E12 -> 24640.72 | F12: ='Budget - Grantville'!F12+'Budget - Tyler'!F12 -> 25076.663 | G12: ='Budget - Grantville'!G12+'Budget - Tyler'!G12 -> 25482.09 | H12: ='Budget - Grantville'!H12+'Budget - Tyler'!H12 -> 26191.355 | I12: ='Budget - Grantville'!I12+'Budget - Tyler'!I12 -> 26850.972 | ... M12: ='Budget - Grantville'!M12+'Budget - Tyler'!M12 -> 26309.128 | N12: =SUM(B12:M12) -> 307831.59 | O12: =222505.71+46989.65-483.03 -> 269012.33
A13: Other Rent Income | N13: =SUM(B13:M13) -> 0 | O13: =SUM(C13:N13) -> 0
A14: Other Rent Income | N14: =SUM(B14:M14) -> 0 | O14: =SUM(C14:N14) -> 0
A15: Total Rental Income | B15: =SUM(B12:B14) -> 24737.009 | C15: =SUM(C12:C14) -> 24623.314 | D15: =SUM(D12:D14) -> 24517.577 | E15: =SUM(E12:E14) -> 24640.72 | F15: =SUM(F12:F14) -> 25076.663 | G15: =SUM(G12:G14) -> 25482.09 | H15: =SUM(H12:H14) -> 26191.355 | I15: =SUM(I12:I14) -> 26850.972 | ... M15: =SUM(M12:M14) -> 26309.128 | N15: =(((((((((((B15)+(C15))+(D15))+(E15))+(F15))+(G15))+(H15))+(I15))+(J15))+(K15))+(L15))+(M15) -> 307831.59 | O15: =SUM(O12:O14) -> 269012.33
A16: Fee Income
A17: Admin Fees | B17: ='Budget - Grantville'!B17+'Budget - Tyler'!B17 -> 160 | C17: ='Budget - Grantville'!C17+'Budget - Tyler'!C17 -> 220 | D17: ='Budget - Grantville'!D17+'Budget - Tyler'!D17 -> 220 | E17: ='Budget - Grantville'!E17+'Budget - Tyler'!E17 -> 260 | F17: ='Budget - Grantville'!F17+'Budget - Tyler'!F17 -> 300 | G17: ='Budget - Grantville'!G17+'Budget - Tyler'!G17 -> 300 | H17: ='Budget - Grantville'!H17+'Budget - Tyler'!H17 -> 360 | I17: ='Budget - Grantville'!I17+'Budget - Tyler'!I17 -> 360 | ... M17: ='Budget - Grantville'!M17+'Budget - Tyler'!M17 -> 240 | N17: =SUM(B17:M17) -> 3140 | O17: 4175.54
A18: Late Fee Income | B18: ='Budget - Grantville'!B18+'Budget - Tyler'!B18 -> 742.11027 | C18: ='Budget - Grantville'!C18+'Budget - Tyler'!C18 -> 738.69941 | D18: ='Budget - Grantville'!D18+'Budget - Tyler'!D18 -> 735.5273 | E18: ='Budget - Grantville'!E18+'Budget - Tyler'!E18 -> 739.22162 | F18: ='Budget - Grantville'!F18+'Budget - Tyler'!F18 -> 752.2999 | G18: ='Budget - Grantville'!G18+'Budget - Tyler'!G18 -> 764.4627 | H18: ='Budget - Grantville'!H18+'Budget - Tyler'!H18 -> 785.74066 | I18: ='Budget - Grantville'!I18+'Budget - Tyler'!I18 -> 805.52917 | ... M18: ='Budget - Grantville'!M18+'Budget - Tyler'!M18 -> 789.27384 | N18: =SUM(B18:M18) -> 9234.9478 | O18: 8653
A19: Convenience Fee | B19: ='Budget - Grantville'!B19+'Budget - Tyler'!B19 -> 44 | C19: ='Budget - Grantville'!C19+'Budget - Tyler'!C19 -> 43.67 | D19: ='Budget - Grantville'!D19+'Budget - Tyler'!D19 -> 43.3631 | E19: ='Budget - Grantville'!E19+'Budget - Tyler'!E19 -> 43.577683 | F19: ='Budget - Grantville'!F19+'Budget - Tyler'!F19 -> 44.277245 | G19: ='Budget - Grantville'!G19+'Budget - Tyler'!G19 -> 44.927838 | H19: ='Budget - Grantville'!H19+'Budget - Tyler'!H19 -> 46.282889 | I19: ='Budget - Grantville'!I19+'Budget - Tyler'!I19 -> 47.543087 | ... M19: ='Budget - Grantville'!M19+'Budget - Tyler'!M19 -> 46.64444 | N19: =SUM(B19:M19) -> 545.03768 | O19: 95.84
A20: General Fee Income | B20: ='Budget - Grantville'!B20+'Budget - Tyler'!B20 -> 0 | C20: ='Budget - Grantville'!C20+'Budget - Tyler'!C20 -> 0 | D20: ='Budget - Grantville'!D20+'Budget - Tyler'!D20 -> 0 | E20: ='Budget - Grantville'!E20+'Budget - Tyler'!E20 -> 0 | F20: ='Budget - Grantville'!F20+'Budget - Tyler'!F20 -> 0 | G20: ='Budget - Grantville'!G20+'Budget - Tyler'!G20 -> 0 | H20: ='Budget - Grantville'!H20+'Budget - Tyler'!H20 -> 0 | I20: ='Budget - Grantville'!I20+'Budget - Tyler'!I20 -> 0 | ... M20: ='Budget - Grantville'!M20+'Budget - Tyler'!M20 -> 0 | N20: =SUM(B20:M20) -> 0 | O20: 843.48
A21: Other Fee | B21: ='Budget - Grantville'!B21+'Budget - Tyler'!B21 -> 0 | C21: ='Budget - Grantville'!C21+'Budget - Tyler'!C21 -> 0 | D21: ='Budget - Grantville'!D21+'Budget - Tyler'!D21 -> 0 | E21: ='Budget - Grantville'!E21+'Budget - Tyler'!E21 -> 0 | F21: ='Budget - Grantville'!F21+'Budget - Tyler'!F21 -> 0 | G21: ='Budget - Grantville'!G21+'Budget - Tyler'!G21 -> 0 | H21: ='Budget - Grantville'!H21+'Budget - Tyler'!H21 -> 0 | I21: ='Budget - Grantville'!I21+'Budget - Tyler'!I21 -> 0 | ... M21: ='Budget - Grantville'!M21+'Budget - Tyler'!M21 -> 0 | N21: =SUM(B21:M21) -> 0 | O21: =SUM(C21:N21) -> 0
A22: Total Fee Income | B22: =SUM(B17:B21) -> 946.11027 | C22: =SUM(C17:C21) -> 1002.3694 | D22: =SUM(D17:D21) -> 998.8904 | E22: =SUM(E17:E21) -> 1042.7993 | F22: =SUM(F17:F21) -> 1096.5771 | G22: =SUM(G17:G21) -> 1109.3905 | H22: =SUM(H17:H21) -> 1192.0236 | I22: =SUM(I17:I21) -> 1213.0723 | ... M22: =SUM(M17:M21) -> 1075.9183 | N22: =(((((((((((B22)+(C22))+(D22))+(E22))+(F22))+(G22))+(H22))+(I22))+(J22))+(K22))+(L22))+(M22) -> 12919.985 | O22: =SUM(O17:O21) -> 13767.86
A23: Ancillary Income
A24: Merchandise Income | B24: ='Budget - Grantville'!B24+'Budget - Tyler'!B24 -> 0 | C24: ='Budget - Grantville'!C24+'Budget - Tyler'!C24 -> 0 | D24: ='Budget - Grantville'!D24+'Budget - Tyler'!D24 -> 0 | E24: ='Budget - Grantville'!E24+'Budget - Tyler'!E24 -> 0 | F24: ='Budget - Grantville'!F24+'Budget - Tyler'!F24 -> 0 | G24: ='Budget - Grantville'!G24+'Budget - Tyler'!G24 -> 0 | H24: ='Budget - Grantville'!H24+'Budget - Tyler'!H24 -> 0 | I24: ='Budget - Grantville'!I24+'Budget - Tyler'!I24 -> 0 | ... M24: ='Budget - Grantville'!M24+'Budget - Tyler'!M24 -> 0 | N24: =SUM(B24:M24) -> 0 | O24: =SUM(C24:N24) -> 0
A25: Tenant Protection | B25: ='Budget - Grantville'!B25+'Budget - Tyler'!B25 -> 816.55 | C25: ='Budget - Grantville'!C25+'Budget - Tyler'!C25 -> 810.6415 | D25: ='Budget - Grantville'!D25+'Budget - Tyler'!D25 -> 805.1466 | E25: ='Budget - Grantville'!E25+'Budget - Tyler'!E25 -> 809.13633 | F25: ='Budget - Grantville'!F25+'Budget - Tyler'!F25 -> 822.24679 | G25: ='Budget - Grantville'!G25+'Budget - Tyler'!G25 -> 834.43951 | H25: ='Budget - Grantville'!H25+'Budget - Tyler'!H25 -> 859.42875 | I25: ='Budget - Grantville'!I25+'Budget - Tyler'!I25 -> 882.66874 | ... M25: ='Budget - Grantville'!M25+'Budget - Tyler'!M25 -> 865.88176 | N25: =SUM(B25:M25) -> 10119.014 | O25: 7232.79
A26: Truck Rentals | B26: ='Budget - Grantville'!B26+'Budget - Tyler'!B26 -> 0 | C26: ='Budget - Grantville'!C26+'Budget - Tyler'!C26 -> 0 | D26: ='Budget - Grantville'!D26+'Budget - Tyler'!D26 -> 0 | E26: ='Budget - Grantville'!E26+'Budget - Tyler'!E26 -> 0 | F26: ='Budget - Grantville'!F26+'Budget - Tyler'!F26 -> 0 | G26: ='Budget - Grantville'!G26+'Budget - Tyler'!G26 -> 0 | H26: ='Budget - Grantville'!H26+'Budget - Tyler'!H26 -> 0 | I26: ='Budget - Grantville'!I26+'Budget - Tyler'!I26 -> 0 | ... M26: ='Budget - Grantville'!M26+'Budget - Tyler'!M26 -> 0 | N26: =SUM(B26:M26) -> 0 | O26: =SUM(C26:N26) -> 0
A27: Propane Sales | B27: ='Budget - Grantville'!B27+'Budget - Tyler'!B27 -> 0 | C27: ='Budget - Grantville'!C27+'Budget - Tyler'!C27 -> 0 | D27: ='Budget - Grantville'!D27+'Budget - Tyler'!D27 -> 0 | E27: ='Budget - Grantville'!E27+'Budget - Tyler'!E27 -> 0 | F27: ='Budget - Grantville'!F27+'Budget - Tyler'!F27 -> 0 | G27: ='Budget - Grantville'!G27+'Budget - Tyler'!G27 -> 0 | H27: ='Budget - Grantville'!H27+'Budget - Tyler'!H27 -> 0 | I27: ='Budget - Grantville'!I27+'Budget - Tyler'!I27 -> 0 | ... M27: ='Budget - Grantville'!M27+'Budget - Tyler'!M27 -> 0 | N27: =SUM(B27:M27) -> 0 | O27: =SUM(C27:N27) -> 0
A28: Other Income Sources | B28: ='Budget - Grantville'!B28+'Budget - Tyler'!B28 -> 0 | C28: ='Budget - Grantville'!C28+'Budget - Tyler'!C28 -> 0 | D28: ='Budget - Grantville'!D28+'Budget - Tyler'!D28 -> 0 | E28: ='Budget - Grantville'!E28+'Budget - Tyler'!E28 -> 0 | F28: ='Budget - Grantville'!F28+'Budget - Tyler'!F28 -> 0 | G28: ='Budget - Grantville'!G28+'Budget - Tyler'!G28 -> 0 | H28: ='Budget - Grantville'!H28+'Budget - Tyler'!H28 -> 0 | I28: ='Budget - Grantville'!I28+'Budget - Tyler'!I28 -> 0 | ... M28: ='Budget - Grantville'!M28+'Budget - Tyler'!M28 -> 0 | N28: =SUM(B28:M28) -> 0 | O28: =SUM(C28:N28) -> 0
A29: Other Income Sources | B29: ='Budget - Grantville'!B29+'Budget - Tyler'!B29 -> 0 | C29: ='Budget - Grantville'!C29+'Budget - Tyler'!C29 -> 0 | D29: ='Budget - Grantville'!D29+'Budget - Tyler'!D29 -> 0 | E29: ='Budget - Grantville'!E29+'Budget - Tyler'!E29 -> 0 | F29: ='Budget - Grantville'!F29+'Budget - Tyler'!F29 -> 0 | G29: ='Budget - Grantville'!G29+'Budget - Tyler'!G29 -> 0 | H29: ='Budget - Grantville'!H29+'Budget - Tyler'!H29 -> 0 | I29: ='Budget - Grantville'!I29+'Budget - Tyler'!I29 -> 0 | ... M29: ='Budget - Grantville'!M29+'Budget - Tyler'!M29 -> 0 | N29: =SUM(B29:M29) -> 0 | O29: =SUM(C29:N29) -> 0
A30: Total Ancillary Income | B30: =SUM(B24:B29) -> 816.55 | C30: =SUM(C24:C29) -> 810.6415 | D30: =SUM(D24:D29) -> 805.1466 | E30: =SUM(E24:E29) -> 809.13633 | F30: =SUM(F24:F29) -> 822.24679 | G30: =SUM(G24:G29) -> 834.43951 | H30: =SUM(H24:H29) -> 859.42875 | I30: =SUM(I24:I29) -> 882.66874 | ... M30: =SUM(M24:M29) -> 865.88176 | N30: =(((((((((((B30)+(C30))+(D30))+(E30))+(F30))+(G30))+(H30))+(I30))+(J30))+(K30))+(L30))+(M30) -> 10119.014 | O30: =SUM(O24:O29) -> 7232.79
A31: Total Revenue | B31: =B15+B22+B30 -> 26499.669 | C31: =C15+C22+C30 -> 26436.325 | D31: =D15+D22+D30 -> 26321.614 | E31: =E15+E22+E30 -> 26492.656 | F31: =F15+F22+F30 -> 26995.487 | G31: =G15+G22+G30 -> 27425.92 | H31: =H15+H22+H30 -> 28242.808 | I31: =I15+I22+I30 -> 28946.713 | ... M31: =M15+M22+M30 -> 28250.928 | N31: =SUM(B31:M31) -> 330870.59 | O31: =O15+O22+O30 -> 290012.98
A33: Expense Projection
A34: Advertising/Marketing
A35: PPC (payperclick) | B35: ='Budget - Grantville'!B35+'Budget - Tyler'!B35 -> 600 | C35: ='Budget - Grantville'!C35+'Budget - Tyler'!C35 -> 600 | D35: ='Budget - Grantville'!D35+'Budget - Tyler'!D35 -> 600 | E35: ='Budget - Grantville'!E35+'Budget - Tyler'!E35 -> 600 | F35: ='Budget - Grantville'!F35+'Budget - Tyler'!F35 -> 600 | G35: ='Budget - Grantville'!G35+'Budget - Tyler'!G35 -> 600 | H35: ='Budget - Grantville'!H35+'Budget - Tyler'!H35 -> 600 | I35: ='Budget - Grantville'!I35+'Budget - Tyler'!I35 -> 600 | ... M35: ='Budget - Grantville'!M35+'Budget - Tyler'!M35 -> 600 | N35: =(((((((((((B35)+(C35))+(D35))+(E35))+(F35))+(G35))+(H35))+(I35))+(J35))+(K35))+(L35))+(M35) -> 7200
A36: Print Materials | B36: ='Budget - Grantville'!B36+'Budget - Tyler'!B36 -> 0 | C36: ='Budget - Grantville'!C36+'Budget - Tyler'!C36 -> 0 | D36: ='Budget - Grantville'!D36+'Budget - Tyler'!D36 -> 200 | E36: ='Budget - Grantville'!E36+'Budget - Tyler'!E36 -> 0 | F36: ='Budget - Grantville'!F36+'Budget - Tyler'!F36 -> 0 | G36: ='Budget - Grantville'!G36+'Budget - Tyler'!G36 -> 0 | H36: ='Budget - Grantville'!H36+'Budget - Tyler'!H36 -> 200 | I36: ='Budget - Grantville'!I36+'Budget - Tyler'!I36 -> 0 | ... M36: ='Budget - Grantville'!M36+'Budget - Tyler'!M36 -> 0 | N36: =(((((((((((B36)+(C36))+(D36))+(E36))+(F36))+(G36))+(H36))+(I36))+(J36))+(K36))+(L36))+(M36) -> 600 | O36: 488.1
A37: Reputation & Social | B37: ='Budget - Grantville'!B37+'Budget - Tyler'!B37 -> 0 | C37: ='Budget - Grantville'!C37+'Budget - Tyler'!C37 -> 0 | D37: ='Budget - Grantville'!D37+'Budget - Tyler'!D37 -> 0 | E37: ='Budget - Grantville'!E37+'Budget - Tyler'!E37 -> 0 | F37: ='Budget - Grantville'!F37+'Budget - Tyler'!F37 -> 0 | G37: ='Budget - Grantville'!G37+'Budget - Tyler'!G37 -> 0 | H37: ='Budget - Grantville'!H37+'Budget - Tyler'!H37 -> 0 | I37: ='Budget - Grantville'!I37+'Budget - Tyler'!I37 -> 0 | ... M37: ='Budget - Grantville'!M37+'Budget - Tyler'!M37 -> 0 | N37: =(((((((((((B37)+(C37))+(D37))+(E37))+(F37))+(G37))+(H37))+(I37))+(J37))+(K37))+(L37))+(M37) -> 0
A38: Website | B38: ='Budget - Grantville'!B38+'Budget - Tyler'!B38 -> 600 | C38: ='Budget - Grantville'!C38+'Budget - Tyler'!C38 -> 600 | D38: ='Budget - Grantville'!D38+'Budget - Tyler'!D38 -> 600 | E38: ='Budget - Grantville'!E38+'Budget - Tyler'!E38 -> 600 | F38: ='Budget - Grantville'!F38+'Budget - Tyler'!F38 -> 600 | G38: ='Budget - Grantville'!G38+'Budget - Tyler'!G38 -> 600 | H38: ='Budget - Grantville'!H38+'Budget - Tyler'!H38 -> 600 | I38: ='Budget - Grantville'!I38+'Budget - Tyler'!I38 -> 600 | ... M38: ='Budget - Grantville'!M38+'Budget - Tyler'!M38 -> 600 | N38: =(((((((((((B38)+(C38))+(D38))+(E38))+(F38))+(G38))+(H38))+(I38))+(J38))+(K38))+(L38))+(M38) -> 7200 | O38: 6716
A39: Sparefoot | B39: ='Budget - Grantville'!B39+'Budget - Tyler'!B39 -> 0 | C39: ='Budget - Grantville'!C39+'Budget - Tyler'!C39 -> 0 | D39: ='Budget - Grantville'!D39+'Budget - Tyler'!D39 -> 0 | E39: ='Budget - Grantville'!E39+'Budget - Tyler'!E39 -> 0 | F39: ='Budget - Grantville'!F39+'Budget - Tyler'!F39 -> 0 | G39: ='Budget - Grantville'!G39+'Budget - Tyler'!G39 -> 0 | H39: ='Budget - Grantville'!H39+'Budget - Tyler'!H39 -> 0 | I39: ='Budget - Grantville'!I39+'Budget - Tyler'!I39 -> 0 | ... M39: ='Budget - Grantville'!M39+'Budget - Tyler'!M39 -> 0 | N39: =(((((((((((B39)+(C39))+(D39))+(E39))+(F39))+(G39))+(H39))+(I39))+(J39))+(K39))+(L39))+(M39) -> 0 | O39: 11409.35
A40: Advertising/Marketing | B40: =SUM(B35:B39) -> 1200 | C40: =SUM(C35:C39) -> 1200 | D40: =SUM(D35:D39) -> 1400 | E40: =SUM(E35:E39) -> 1200 | F40: =SUM(F35:F39) -> 1200 | G40: =SUM(G35:G39) -> 1200 | H40: =SUM(H35:H39) -> 1400 | I40: =SUM(I35:I39) -> 1200 | ... M40: =SUM(M35:M39) -> 1200 | N40: =(((((((((((B40)+(C40))+(D40))+(E40))+(F40))+(G40))+(H40))+(I40))+(J40))+(K40))+(L40))+(M40) -> 15000 | O40: =SUM(O35:O39) -> 18613.45
A41: Legal & Professional Fees | N41: =(((((((((((B41)+(C41))+(D41))+(E41))+(F41))+(G41))+(H41))+(I41))+(J41))+(K41))+(L41))+(M41) -> 0
A42: Auction Expenses | B42: ='Budget - Grantville'!B42+'Budget - Tyler'!B42 -> 200 | C42: ='Budget - Grantville'!C42+'Budget - Tyler'!C42 -> 200 | D42: ='Budget - Grantville'!D42+'Budget - Tyler'!D42 -> 200 | E42: ='Budget - Grantville'!E42+'Budget - Tyler'!E42 -> 200 | F42: ='Budget - Grantville'!F42+'Budget - Tyler'!F42 -> 200 | G42: ='Budget - Grantville'!G42+'Budget - Tyler'!G42 -> 200 | H42: ='Budget - Grantville'!H42+'Budget - Tyler'!H42 -> 200 | I42: ='Budget - Grantville'!I42+'Budget - Tyler'!I42 -> 200 | ... M42: ='Budget - Grantville'!M42+'Budget - Tyler'!M42 -> 200 | N42: =(((((((((((B42)+(C42))+(D42))+(E42))+(F42))+(G42))+(H42))+(I42))+(J42))+(K42))+(L42))+(M42) -> 2400 | O42: 2131.2
A43: Management Services | B43: ='Budget - Grantville'!B43+'Budget - Tyler'!B43 -> 2080.0296 | C43: ='Budget - Grantville'!C43+'Budget - Tyler'!C43 -> 2090.2783 | D43: ='Budget - Grantville'!D43+'Budget - Tyler'!D43 -> 2096.4617 | E43: ='Budget - Grantville'!E43+'Budget - Tyler'!E43 -> 2102.2122 | F43: ='Budget - Grantville'!F43+'Budget - Tyler'!F43 -> 2130.4179 | G43: ='Budget - Grantville'!G43+'Budget - Tyler'!G43 -> 2154.4172 | H43: ='Budget - Grantville'!H43+'Budget - Tyler'!H43 -> 2176.7365 | I43: ='Budget - Grantville'!I43+'Budget - Tyler'!I43 -> 2197.4935 | ... M43: ='Budget - Grantville'!M43+'Budget - Tyler'!M43 -> 2164.4615 | N43: =(((((((((((B43)+(C43))+(D43))+(E43))+(F43))+(G43))+(H43))+(I43))+(J43))+(K43))+(L43))+(M43) -> 25709.025 | O43: 24000
A44: Call Center | B44: ='Budget - Grantville'!B44+'Budget - Tyler'!B44 -> 0 | C44: ='Budget - Grantville'!C44+'Budget - Tyler'!C44 -> 0 | D44: ='Budget - Grantville'!D44+'Budget - Tyler'!D44 -> 0 | E44: ='Budget - Grantville'!E44+'Budget - Tyler'!E44 -> 0 | F44: ='Budget - Grantville'!F44+'Budget - Tyler'!F44 -> 0 | G44: ='Budget - Grantville'!G44+'Budget - Tyler'!G44 -> 0 | H44: ='Budget - Grantville'!H44+'Budget - Tyler'!H44 -> 0 | I44: ='Budget - Grantville'!I44+'Budget - Tyler'!I44 -> 0 | ... M44: ='Budget - Grantville'!M44+'Budget - Tyler'!M44 -> 0 | N44: =(((((((((((B44)+(C44))+(D44))+(E44))+(F44))+(G44))+(H44))+(I44))+(J44))+(K44))+(L44))+(M44) -> 0
A45: Legal Fees | B45: ='Budget - Grantville'!B45+'Budget - Tyler'!B45 -> 0 | C45: ='Budget - Grantville'!C45+'Budget - Tyler'!C45 -> 0 | D45: ='Budget - Grantville'!D45+'Budget - Tyler'!D45 -> 0 | E45: ='Budget - Grantville'!E45+'Budget - Tyler'!E45 -> 0 | F45: ='Budget - Grantville'!F45+'Budget - Tyler'!F45 -> 0 | G45: ='Budget - Grantville'!G45+'Budget - Tyler'!G45 -> 0 | H45: ='Budget - Grantville'!H45+'Budget - Tyler'!H45 -> 300 | I45: ='Budget - Grantville'!I45+'Budget - Tyler'!I45 -> 150 | ... M45: ='Budget - Grantville'!M45+'Budget - Tyler'!M45 -> 0 | N45: =(((((((((((B45)+(C45))+(D45))+(E45))+(F45))+(G45))+(H45))+(I45))+(J45))+(K45))+(L45))+(M45) -> 450 | O45: 600
A46: Accounting Fees | B46: ='Budget - Grantville'!B46+'Budget - Tyler'!B46 -> 0 | C46: ='Budget - Grantville'!C46+'Budget - Tyler'!C46 -> 0 | D46: ='Budget - Grantville'!D46+'Budget - Tyler'!D46 -> 0 | E46: ='Budget - Grantville'!E46+'Budget - Tyler'!E46 -> 0 | F46: ='Budget - Grantville'!F46+'Budget - Tyler'!F46 -> 0 | G46: ='Budget - Grantville'!G46+'Budget - Tyler'!G46 -> 0 | H46: ='Budget - Grantville'!H46+'Budget - Tyler'!H46 -> 300 | I46: ='Budget - Grantville'!I46+'Budget - Tyler'!I46 -> 0 | ... M46: ='Budget - Grantville'!M46+'Budget - Tyler'!M46 -> 0 | N46: =(((((((((((B46)+(C46))+(D46))+(E46))+(F46))+(G46))+(H46))+(I46))+(J46))+(K46))+(L46))+(M46) -> 300 | O46: 303.11
A47: Total Legal & Professional Fees | B47: =SUM(B42:B46) -> 2280.0296 | C47: =SUM(C42:C46) -> 2290.2783 | D47: =SUM(D42:D46) -> 2296.4617 | E47: =SUM(E42:E46) -> 2302.2122 | F47: =SUM(F42:F46) -> 2330.4179 | G47: =SUM(G42:G46) -> 2354.4172 | H47: =SUM(H42:H46) -> 2976.7365 | I47: =SUM(I42:I46) -> 2547.4935 | ... M47: =SUM(M42:M46) -> 2364.4615 | N47: =(((((((((((B47)+(C47))+(D47))+(E47))+(F47))+(G47))+(H47))+(I47))+(J47))+(K47))+(L47))+(M47) -> 28859.025 | O47: =SUM(O42:O46) -> 27034.31
A48: Office/Site
A49: Cost of Merchandise Sold | B49: ='Budget - Grantville'!B49+'Budget - Tyler'!B49 -> 0 | C49: ='Budget - Grantville'!C49+'Budget - Tyler'!C49 -> 0 | D49: ='Budget - Grantville'!D49+'Budget - Tyler'!D49 -> 0 | E49: ='Budget - Grantville'!E49+'Budget - Tyler'!E49 -> 0 | F49: ='Budget - Grantville'!F49+'Budget - Tyler'!F49 -> 0 | G49: ='Budget - Grantville'!G49+'Budget - Tyler'!G49 -> 0 | H49: ='Budget - Grantville'!H49+'Budget - Tyler'!H49 -> 0 | I49: ='Budget - Grantville'!I49+'Budget - Tyler'!I49 -> 0 | ... M49: ='Budget - Grantville'!M49+'Budget - Tyler'!M49 -> 0 | N49: =(((((((((((B49)+(C49))+(D49))+(E49))+(F49))+(G49))+(H49))+(I49))+(J49))+(K49))+(L49))+(M49) -> 0
A50: Site Supplies | B50: ='Budget - Grantville'!B50+'Budget - Tyler'!B50 -> 100 | C50: ='Budget - Grantville'!C50+'Budget - Tyler'!C50 -> 100 | D50: ='Budget - Grantville'!D50+'Budget - Tyler'!D50 -> 100 | E50: ='Budget - Grantville'!E50+'Budget - Tyler'!E50 -> 100 | F50: ='Budget - Grantville'!F50+'Budget - Tyler'!F50 -> 100 | G50: ='Budget - Grantville'!G50+'Budget - Tyler'!G50 -> 100 | H50: ='Budget - Grantville'!H50+'Budget - Tyler'!H50 -> 100 | I50: ='Budget - Grantville'!I50+'Budget - Tyler'!I50 -> 100 | ... M50: ='Budget - Grantville'!M50+'Budget - Tyler'!M50 -> 100 | N50: =(((((((((((B50)+(C50))+(D50))+(E50))+(F50))+(G50))+(H50))+(I50))+(J50))+(K50))+(L50))+(M50) -> 1200 | O50: =976.14+1400.39 -> 2376.53
A51: Office Supplies | B51: ='Budget - Grantville'!B51+'Budget - Tyler'!B51 -> 100 | C51: ='Budget - Grantville'!C51+'Budget - Tyler'!C51 -> 100 | D51: ='Budget - Grantville'!D51+'Budget - Tyler'!D51 -> 100 | E51: ='Budget - Grantville'!E51+'Budget - Tyler'!E51 -> 100 | F51: ='Budget - Grantville'!F51+'Budget - Tyler'!F51 -> 100 | G51: ='Budget - Grantville'!G51+'Budget - Tyler'!G51 -> 100 | H51: ='Budget - Grantville'!H51+'Budget - Tyler'!H51 -> 100 | I51: ='Budget - Grantville'!I51+'Budget - Tyler'!I51 -> 100 | ... M51: ='Budget - Grantville'!M51+'Budget - Tyler'!M51 -> 100 | N51: =(((((((((((B51)+(C51))+(D51))+(E51))+(F51))+(G51))+(H51))+(I51))+(J51))+(K51))+(L51))+(M51) -> 1200 | O51: =72.45+466 -> 538.45
A52: Business Licenses | B52: ='Budget - Grantville'!B52+'Budget - Tyler'!B52 -> 0 | C52: ='Budget - Grantville'!C52+'Budget - Tyler'!C52 -> 0 | D52: ='Budget - Grantville'!D52+'Budget - Tyler'!D52 -> 0 | E52: ='Budget - Grantville'!E52+'Budget - Tyler'!E52 -> 0 | F52: ='Budget - Grantville'!F52+'Budget - Tyler'!F52 -> 0 | G52: ='Budget - Grantville'!G52+'Budget - Tyler'!G52 -> 0 | H52: ='Budget - Grantville'!H52+'Budget - Tyler'!H52 -> 0 | I52: ='Budget - Grantville'!I52+'Budget - Tyler'!I52 -> 0 | ... M52: ='Budget - Grantville'!M52+'Budget - Tyler'!M52 -> 0 | O52: 49.95
A53: Total Office/Site | B53: =SUM(B49:B52) -> 200 | C53: =SUM(C49:C52) -> 200 | D53: =SUM(D49:D52) -> 200 | E53: =SUM(E49:E52) -> 200 | F53: =SUM(F49:F52) -> 200 | G53: =SUM(G49:G52) -> 200 | H53: =SUM(H49:H52) -> 200 | I53: =SUM(I49:I52) -> 200 | ... M53: =SUM(M49:M52) -> 200 | N53: =(((((((((((B53)+(C53))+(D53))+(E53))+(F53))+(G53))+(H53))+(I53))+(J53))+(K53))+(L53))+(M53) -> 2400 | O53: =SUM(O49:O52) -> 2964.93
A54: Repairs and Maintenance
A55: Lawn/Snow | B55: ='Budget - Grantville'!B57+'Budget - Tyler'!B57 -> 600 | C55: ='Budget - Grantville'!C57+'Budget - Tyler'!C57 -> 600 | D55: ='Budget - Grantville'!D57+'Budget - Tyler'!D57 -> 600 | E55: ='Budget - Grantville'!E57+'Budget - Tyler'!E57 -> 600 | F55: ='Budget - Grantville'!F57+'Budget - Tyler'!F57 -> 600 | G55: ='Budget - Grantville'!G57+'Budget - Tyler'!G57 -> 600 | H55: ='Budget - Grantville'!H57+'Budget - Tyler'!H57 -> 600 | I55: ='Budget - Grantville'!I57+'Budget - Tyler'!I57 -> 600 | ... M55: ='Budget - Grantville'!M57+'Budget - Tyler'!M57 -> 600 | N55: =(((((((((((B55)+(C55))+(D55))+(E55))+(F55))+(G55))+(H55))+(I55))+(J55))+(K55))+(L55))+(M55) -> 7200 | O55: =3543.6+2575 -> 6118.6
A56: Elevator | B56: ='Budget - Grantville'!B58+'Budget - Tyler'!B58 -> 0 | C56: ='Budget - Grantville'!C58+'Budget - Tyler'!C58 -> 0 | D56: ='Budget - Grantville'!D58+'Budget - Tyler'!D58 -> 0 | E56: ='Budget - Grantville'!E58+'Budget - Tyler'!E58 -> 0 | F56: ='Budget - Grantville'!F58+'Budget - Tyler'!F58 -> 0 | G56: ='Budget - Grantville'!G58+'Budget - Tyler'!G58 -> 0 | H56: ='Budget - Grantville'!H58+'Budget - Tyler'!H58 -> 0 | I56: ='Budget - Grantville'!I58+'Budget - Tyler'!I58 -> 0 | ... M56: ='Budget - Grantville'!M58+'Budget - Tyler'!M58 -> 0 | N56: =(((((((((((B56)+(C56))+(D56))+(E56))+(F56))+(G56))+(H56))+(I56))+(J56))+(K56))+(L56))+(M56) -> 0
A57: Gate & Fence | B57: ='Budget - Grantville'!B59+'Budget - Tyler'!B59 -> 0 | C57: ='Budget - Grantville'!C59+'Budget - Tyler'!C59 -> 0 | D57: ='Budget - Grantville'!D59+'Budget - Tyler'!D59 -> 0 | E57: ='Budget - Grantville'!E59+'Budget - Tyler'!E59 -> 0 | F57: ='Budget - Grantville'!F59+'Budget - Tyler'!F59 -> 0 | G57: ='Budget - Grantville'!G59+'Budget - Tyler'!G59 -> 0 | H57: ='Budget - Grantville'!H59+'Budget - Tyler'!H59 -> 0 | I57: ='Budget - Grantville'!I59+'Budget - Tyler'!I59 -> 0 | ... M57: ='Budget - Grantville'!M59+'Budget - Tyler'!M59 -> 0
A58: Unit Doors | B58: ='Budget - Grantville'!B60+'Budget - Tyler'!B60 -> 0 | C58: ='Budget - Grantville'!C60+'Budget - Tyler'!C60 -> 0 | D58: ='Budget - Grantville'!D60+'Budget - Tyler'!D60 -> 0 | E58: ='Budget - Grantville'!E60+'Budget - Tyler'!E60 -> 0 | F58: ='Budget - Grantville'!F60+'Budget - Tyler'!F60 -> 0 | G58: ='Budget - Grantville'!G60+'Budget - Tyler'!G60 -> 0 | H58: ='Budget - Grantville'!H60+'Budget - Tyler'!H60 -> 0 | I58: ='Budget - Grantville'!I60+'Budget - Tyler'!I60 -> 0 | ... M58: ='Budget - Grantville'!M60+'Budget - Tyler'!M60 -> 0
A59: Security System | B59: ='Budget - Grantville'!B61+'Budget - Tyler'!B61 -> 0 | C59: ='Budget - Grantville'!C61+'Budget - Tyler'!C61 -> 0 | D59: ='Budget - Grantville'!D61+'Budget - Tyler'!D61 -> 0 | E59: ='Budget - Grantville'!E61+'Budget - Tyler'!E61 -> 0 | F59: ='Budget - Grantville'!F61+'Budget - Tyler'!F61 -> 0 | G59: ='Budget - Grantville'!G61+'Budget - Tyler'!G61 -> 0 | H59: ='Budget - Grantville'!H61+'Budget - Tyler'!H61 -> 0 | I59: ='Budget - Grantville'!I61+'Budget - Tyler'!I61 -> 0 | ... M59: ='Budget - Grantville'!M61+'Budget - Tyler'!M61 -> 0
A60: HVAC | B60: ='Budget - Grantville'!B62+'Budget - Tyler'!B62 -> 0 | C60: ='Budget - Grantville'!C62+'Budget - Tyler'!C62 -> 0 | D60: ='Budget - Grantville'!D62+'Budget - Tyler'!D62 -> 0 | E60: ='Budget - Grantville'!E62+'Budget - Tyler'!E62 -> 0 | F60: ='Budget - Grantville'!F62+'Budget - Tyler'!F62 -> 0 | G60: ='Budget - Grantville'!G62+'Budget - Tyler'!G62 -> 0 | H60: ='Budget - Grantville'!H62+'Budget - Tyler'!H62 -> 0 | I60: ='Budget - Grantville'!I62+'Budget - Tyler'!I62 -> 0 | ... M60: ='Budget - Grantville'!M62+'Budget - Tyler'!M62 -> 0
A61: Pest Control | B61: ='Budget - Grantville'!B63+'Budget - Tyler'!B63 -> 0 | C61: ='Budget - Grantville'!C63+'Budget - Tyler'!C63 -> 0 | D61: ='Budget - Grantville'!D63+'Budget - Tyler'!D63 -> 0 | E61: ='Budget - Grantville'!E63+'Budget - Tyler'!E63 -> 0 | F61: ='Budget - Grantville'!F63+'Budget - Tyler'!F63 -> 0 | G61: ='Budget - Grantville'!G63+'Budget - Tyler'!G63 -> 0 | H61: ='Budget - Grantville'!H63+'Budget - Tyler'!H63 -> 0 | I61: ='Budget - Grantville'!I63+'Budget - Tyler'!I63 -> 0 | ... M61: ='Budget - Grantville'!M63+'Budget - Tyler'!M63 -> 0 | N61: =(((((((((((B61)+(C61))+(D61))+(E61))+(F61))+(G61))+(H61))+(I61))+(J61))+(K61))+(L61))+(M61) -> 0
A62: Site | B62: ='Budget - Grantville'!B64+'Budget - Tyler'!B64 -> 600 | C62: ='Budget - Grantville'!C64+'Budget - Tyler'!C64 -> 600 | D62: ='Budget - Grantville'!D64+'Budget - Tyler'!D64 -> 600 | E62: ='Budget - Grantville'!E64+'Budget - Tyler'!E64 -> 600 | F62: ='Budget - Grantville'!F64+'Budget - Tyler'!F64 -> 600 | G62: ='Budget - Grantville'!G64+'Budget - Tyler'!G64 -> 600 | H62: ='Budget - Grantville'!H64+'Budget - Tyler'!H64 -> 600 | I62: ='Budget - Grantville'!I64+'Budget - Tyler'!I64 -> 600 | ... M62: ='Budget - Grantville'!M64+'Budget - Tyler'!M64 -> 600 | N62: =(((((((((((B62)+(C62))+(D62))+(E62))+(F62))+(G62))+(H62))+(I62))+(J62))+(K62))+(L62))+(M62) -> 7200 | O62: 8843.08
A63: Trash Hauling | B63: ='Budget - Grantville'!B65+'Budget - Tyler'!B65 -> 0 | C63: ='Budget - Grantville'!C65+'Budget - Tyler'!C65 -> 0 | D63: ='Budget - Grantville'!D65+'Budget - Tyler'!D65 -> 0 | E63: ='Budget - Grantville'!E65+'Budget - Tyler'!E65 -> 0 | F63: ='Budget - Grantville'!F65+'Budget - Tyler'!F65 -> 0 | G63: ='Budget - Grantville'!G65+'Budget - Tyler'!G65 -> 0 | H63: ='Budget - Grantville'!H65+'Budget - Tyler'!H65 -> 0 | I63: ='Budget - Grantville'!I65+'Budget - Tyler'!I65 -> 0 | ... M63: ='Budget - Grantville'!M65+'Budget - Tyler'!M65 -> 0
A64: Total Repairs and Maintenance | B64: =SUM(B55:B63) -> 1200 | C64: =SUM(C55:C63) -> 1200 | D64: =SUM(D55:D63) -> 1200 | E64: =SUM(E55:E63) -> 1200 | F64: =SUM(F55:F63) -> 1200 | G64: =SUM(G55:G63) -> 1200 | H64: =SUM(H55:H63) -> 1200 | I64: =SUM(I55:I63) -> 1200 | ... M64: =SUM(M55:M63) -> 1200 | N64: =(((((((((((B64)+(C64))+(D64))+(E64))+(F64))+(G64))+(H64))+(I64))+(J64))+(K64))+(L64))+(M64) -> 14400 | O64: =SUM(O55:O63) -> 14961.68
A65: Service Charges
A66: Bank Service Charges | B66: ='Budget - Grantville'!B68+'Budget - Tyler'!B68 -> 0 | C66: ='Budget - Grantville'!C68+'Budget - Tyler'!C68 -> 0 | D66: ='Budget - Grantville'!D68+'Budget - Tyler'!D68 -> 0 | E66: ='Budget - Grantville'!E68+'Budget - Tyler'!E68 -> 0 | F66: ='Budget - Grantville'!F68+'Budget - Tyler'!F68 -> 0 | G66: ='Budget - Grantville'!G68+'Budget - Tyler'!G68 -> 0 | H66: ='Budget - Grantville'!H68+'Budget - Tyler'!H68 -> 0 | I66: ='Budget - Grantville'!I68+'Budget - Tyler'!I68 -> 0 | ... M66: ='Budget - Grantville'!M68+'Budget - Tyler'!M68 -> 0 | N66: =(((((((((((B66)+(C66))+(D66))+(E66))+(F66))+(G66))+(H66))+(I66))+(J66))+(K66))+(L66))+(M66) -> 0 | O66: 393.39
A67: Credit Card Service Fees | B67: ='Budget - Grantville'!B69+'Budget - Tyler'!B69 -> 715.49107 | C67: ='Budget - Grantville'!C69+'Budget - Tyler'!C69 -> 713.78076 | D67: ='Budget - Grantville'!D69+'Budget - Tyler'!D69 -> 710.68357 | E67: ='Budget - Grantville'!E69+'Budget - Tyler'!E69 -> 715.30172 | F67: ='Budget - Grantville'!F69+'Budget - Tyler'!F69 -> 728.87816 | G67: ='Budget - Grantville'!G69+'Budget - Tyler'!G69 -> 740.49985 | H67: ='Budget - Grantville'!H69+'Budget - Tyler'!H69 -> 762.55581 | I67: ='Budget - Grantville'!I69+'Budget - Tyler'!I69 -> 781.56126 | ... M67: ='Budget - Grantville'!M69+'Budget - Tyler'!M69 -> 762.77505 | N67: =N31*0.02 -> 6617.4118 | O67: 7951.4
A68: Total Service Charges | B68: =SUM(B66:B67) -> 715.49107 | C68: =SUM(C66:C67) -> 713.78076 | D68: =SUM(D66:D67) -> 710.68357 | E68: =SUM(E66:E67) -> 715.30172 | F68: =SUM(F66:F67) -> 728.87816 | G68: =SUM(G66:G67) -> 740.49985 | H68: =SUM(H66:H67) -> 762.55581 | I68: =SUM(I66:I67) -> 781.56126 | ... M68: =SUM(M66:M67) -> 762.77505 | N68: =(((((((((((B68)+(C68))+(D68))+(E68))+(F68))+(G68))+(H68))+(I68))+(J68))+(K68))+(L68))+(M68) -> 8933.506 | O68: =SUM(O66:O67) -> 8344.79
A69: Software
A70: Gate Software | B70: ='Budget - Grantville'!B72+'Budget - Tyler'!B72 -> 90 | C70: ='Budget - Grantville'!C72+'Budget - Tyler'!C72 -> 90 | D70: ='Budget - Grantville'!D72+'Budget - Tyler'!D72 -> 90 | E70: ='Budget - Grantville'!E72+'Budget - Tyler'!E72 -> 90 | F70: ='Budget - Grantville'!F72+'Budget - Tyler'!F72 -> 90 | G70: ='Budget - Grantville'!G72+'Budget - Tyler'!G72 -> 90 | H70: ='Budget - Grantville'!H72+'Budget - Tyler'!H72 -> 90 | I70: ='Budget - Grantville'!I72+'Budget - Tyler'!I72 -> 90 | ... M70: ='Budget - Grantville'!M72+'Budget - Tyler'!M72 -> 90 | N70: =(((((((((((B70)+(C70))+(D70))+(E70))+(F70))+(G70))+(H70))+(I70))+(J70))+(K70))+(L70))+(M70) -> 1080 | O70: 540
A71: Collection Software | B71: ='Budget - Grantville'!B73+'Budget - Tyler'!B73 -> 0 | C71: ='Budget - Grantville'!C73+'Budget - Tyler'!C73 -> 0 | D71: ='Budget - Grantville'!D73+'Budget - Tyler'!D73 -> 0 | E71: ='Budget - Grantville'!E73+'Budget - Tyler'!E73 -> 0 | F71: ='Budget - Grantville'!F73+'Budget - Tyler'!F73 -> 0 | G71: ='Budget - Grantville'!G73+'Budget - Tyler'!G73 -> 0 | H71: ='Budget - Grantville'!H73+'Budget - Tyler'!H73 -> 0 | I71: ='Budget - Grantville'!I73+'Budget - Tyler'!I73 -> 0 | ... M71: ='Budget - Grantville'!M73+'Budget - Tyler'!M73 -> 0 | N71: =(((((((((((B71)+(C71))+(D71))+(E71))+(F71))+(G71))+(H71))+(I71))+(J71))+(K71))+(L71))+(M71) -> 0 | O71: 1000
A72: Accounting/BillPay Software | B72: ='Budget - Grantville'!B74+'Budget - Tyler'!B74 -> 160 | C72: ='Budget - Grantville'!C74+'Budget - Tyler'!C74 -> 160 | D72: ='Budget - Grantville'!D74+'Budget - Tyler'!D74 -> 160 | E72: ='Budget - Grantville'!E74+'Budget - Tyler'!E74 -> 160 | F72: ='Budget - Grantville'!F74+'Budget - Tyler'!F74 -> 160 | G72: ='Budget - Grantville'!G74+'Budget - Tyler'!G74 -> 160 | H72: ='Budget - Grantville'!H74+'Budget - Tyler'!H74 -> 160 | I72: ='Budget - Grantville'!I74+'Budget - Tyler'!I74 -> 160 | ... M72: ='Budget - Grantville'!M74+'Budget - Tyler'!M74 -> 160 | N72: =(((((((((((B72)+(C72))+(D72))+(E72))+(F72))+(G72))+(H72))+(I72))+(J72))+(K72))+(L72))+(M72) -> 1920
A73: Other Software (Swivel) | B73: ='Budget - Grantville'!B75+'Budget - Tyler'!B75 -> 126 | C73: ='Budget - Grantville'!C75+'Budget - Tyler'!C75 -> 126 | D73: ='Budget - Grantville'!D75+'Budget - Tyler'!D75 -> 126 | E73: ='Budget - Grantville'!E75+'Budget - Tyler'!E75 -> 126 | F73: ='Budget - Grantville'!F75+'Budget - Tyler'!F75 -> 126 | G73: ='Budget - Grantville'!G75+'Budget - Tyler'!G75 -> 126 | H73: ='Budget - Grantville'!H75+'Budget - Tyler'!H75 -> 126 | I73: ='Budget - Grantville'!I75+'Budget - Tyler'!I75 -> 126 | ... M73: ='Budget - Grantville'!M75+'Budget - Tyler'!M75 -> 126 | N73: =(((((((((((B73)+(C73))+(D73))+(E73))+(F73))+(G73))+(H73))+(I73))+(J73))+(K73))+(L73))+(M73) -> 1512 | O73: 2049.39
A74: Storage Software | B74: ='Budget - Grantville'!B76+'Budget - Tyler'!B76 -> 240 | C74: ='Budget - Grantville'!C76+'Budget - Tyler'!C76 -> 240 | D74: ='Budget - Grantville'!D76+'Budget - Tyler'!D76 -> 240 | E74: ='Budget - Grantville'!E76+'Budget - Tyler'!E76 -> 240 | F74: ='Budget - Grantville'!F76+'Budget - Tyler'!F76 -> 240 | G74: ='Budget - Grantville'!G76+'Budget - Tyler'!G76 -> 240 | H74: ='Budget - Grantville'!H76+'Budget - Tyler'!H76 -> 240 | I74: ='Budget - Grantville'!I76+'Budget - Tyler'!I76 -> 240 | ... M74: ='Budget - Grantville'!M76+'Budget - Tyler'!M76 -> 240 | N74: =(((((((((((B74)+(C74))+(D74))+(E74))+(F74))+(G74))+(H74))+(I74))+(J74))+(K74))+(L74))+(M74) -> 2880 | O74: 4098.63
A75: Total Software | B75: =SUM(B70:B74) -> 616 | C75: =SUM(C70:C74) -> 616 | D75: =SUM(D70:D74) -> 616 | E75: =SUM(E70:E74) -> 616 | F75: =SUM(F70:F74) -> 616 | G75: =SUM(G70:G74) -> 616 | H75: =SUM(H70:H74) -> 616 | I75: =SUM(I70:I74) -> 616 | ... M75: =SUM(M70:M74) -> 616 | N75: =(((((((((((B75)+(C75))+(D75))+(E75))+(F75))+(G75))+(H75))+(I75))+(J75))+(K75))+(L75))+(M75) -> 7392 | O75: =SUM(O70:O74) -> 7688.02
A76: Staffing
A77: Mileage | B77: ='Budget - Grantville'!B79+'Budget - Tyler'!B79 -> 0 | C77: ='Budget - Grantville'!C79+'Budget - Tyler'!C79 -> 0 | D77: ='Budget - Grantville'!D79+'Budget - Tyler'!D79 -> 0 | E77: ='Budget - Grantville'!E79+'Budget - Tyler'!E79 -> 0 | F77: ='Budget - Grantville'!F79+'Budget - Tyler'!F79 -> 0 | G77: ='Budget - Grantville'!G79+'Budget - Tyler'!G79 -> 0 | H77: ='Budget - Grantville'!H79+'Budget - Tyler'!H79 -> 0 | I77: ='Budget - Grantville'!I79+'Budget - Tyler'!I79 -> 0 | ... M77: ='Budget - Grantville'!M79+'Budget - Tyler'!M79 -> 0 | N77: =(((((((((((B77)+(C77))+(D77))+(E77))+(F77))+(G77))+(H77))+(I77))+(J77))+(K77))+(L77))+(M77) -> 0
A78: Payroll Processing | B78: ='Budget - Grantville'!B80+'Budget - Tyler'!B80 -> 0 | C78: ='Budget - Grantville'!C80+'Budget - Tyler'!C80 -> 0 | D78: ='Budget - Grantville'!D80+'Budget - Tyler'!D80 -> 0 | E78: ='Budget - Grantville'!E80+'Budget - Tyler'!E80 -> 0 | F78: ='Budget - Grantville'!F80+'Budget - Tyler'!F80 -> 0 | G78: ='Budget - Grantville'!G80+'Budget - Tyler'!G80 -> 0 | H78: ='Budget - Grantville'!H80+'Budget - Tyler'!H80 -> 0 | I78: ='Budget - Grantville'!I80+'Budget - Tyler'!I80 -> 0 | ... M78: ='Budget - Grantville'!M80+'Budget - Tyler'!M80 -> 0 | N78: =(((((((((((B78)+(C78))+(D78))+(E78))+(F78))+(G78))+(H78))+(I78))+(J78))+(K78))+(L78))+(M78) -> 0
A79: Payroll Taxes | B79: ='Budget - Grantville'!B81+'Budget - Tyler'!B81 -> 0 | C79: ='Budget - Grantville'!C81+'Budget - Tyler'!C81 -> 0 | D79: ='Budget - Grantville'!D81+'Budget - Tyler'!D81 -> 0 | E79: ='Budget - Grantville'!E81+'Budget - Tyler'!E81 -> 0 | F79: ='Budget - Grantville'!F81+'Budget - Tyler'!F81 -> 0 | G79: ='Budget - Grantville'!G81+'Budget - Tyler'!G81 -> 0 | H79: ='Budget - Grantville'!H81+'Budget - Tyler'!H81 -> 0 | I79: ='Budget - Grantville'!I81+'Budget - Tyler'!I81 -> 0 | ... M79: ='Budget - Grantville'!M81+'Budget - Tyler'!M81 -> 0 | N79: =(((((((((((B79)+(C79))+(D79))+(E79))+(F79))+(G79))+(H79))+(I79))+(J79))+(K79))+(L79))+(M79) -> 0
A80: Staff Costs | B80: ='Budget - Grantville'!B82+'Budget - Tyler'!B82 -> 0 | C80: ='Budget - Grantville'!C82+'Budget - Tyler'!C82 -> 0 | D80: ='Budget - Grantville'!D82+'Budget - Tyler'!D82 -> 0 | E80: ='Budget - Grantville'!E82+'Budget - Tyler'!E82 -> 0 | F80: ='Budget - Grantville'!F82+'Budget - Tyler'!F82 -> 0 | G80: ='Budget - Grantville'!G82+'Budget - Tyler'!G82 -> 0 | H80: ='Budget - Grantville'!H82+'Budget - Tyler'!H82 -> 0 | I80: ='Budget - Grantville'!I82+'Budget - Tyler'!I82 -> 0 | ... M80: ='Budget - Grantville'!M82+'Budget - Tyler'!M82 -> 0 | N80: =(((((((((((B80)+(C80))+(D80))+(E80))+(F80))+(G80))+(H80))+(I80))+(J80))+(K80))+(L80))+(M80) -> 0
A81: Health Insurance | B81: ='Budget - Grantville'!B83+'Budget - Tyler'!B83 -> 0 | C81: ='Budget - Grantville'!C83+'Budget - Tyler'!C83 -> 0 | D81: ='Budget - Grantville'!D83+'Budget - Tyler'!D83 -> 0 | E81: ='Budget - Grantville'!E83+'Budget - Tyler'!E83 -> 0 | F81: ='Budget - Grantville'!F83+'Budget - Tyler'!F83 -> 0 | G81: ='Budget - Grantville'!G83+'Budget - Tyler'!G83 -> 0 | H81: ='Budget - Grantville'!H83+'Budget - Tyler'!H83 -> 0 | I81: ='Budget - Grantville'!I83+'Budget - Tyler'!I83 -> 0 | ... M81: ='Budget - Grantville'!M83+'Budget - Tyler'!M83 -> 0 | N81: =(((((((((((B81)+(C81))+(D81))+(E81))+(F81))+(G81))+(H81))+(I81))+(J81))+(K81))+(L81))+(M81) -> 0
A82: Salary/Wages | B82: ='Budget - Grantville'!B84+'Budget - Tyler'!B84 -> 1200 | C82: ='Budget - Grantville'!C84+'Budget - Tyler'!C84 -> 1200 | D82: ='Budget - Grantville'!D84+'Budget - Tyler'!D84 -> 1200 | E82: ='Budget - Grantville'!E84+'Budget - Tyler'!E84 -> 1200 | F82: ='Budget - Grantville'!F84+'Budget - Tyler'!F84 -> 1200 | G82: ='Budget - Grantville'!G84+'Budget - Tyler'!G84 -> 1200 | H82: ='Budget - Grantville'!H84+'Budget - Tyler'!H84 -> 1200 | I82: ='Budget - Grantville'!I84+'Budget - Tyler'!I84 -> 1200 | ... M82: ='Budget - Grantville'!M84+'Budget - Tyler'!M84 -> 1200 | N82: =(((((((((((B82)+(C82))+(D82))+(E82))+(F82))+(G82))+(H82))+(I82))+(J82))+(K82))+(L82))+(M82) -> 14400 | O82: 14035.85
A83: Workers Comp | B83: ='Budget - Grantville'!B85+'Budget - Tyler'!B85 -> 0 | C83: ='Budget - Grantville'!C85+'Budget - Tyler'!C85 -> 0 | D83: ='Budget - Grantville'!D85+'Budget - Tyler'!D85 -> 0 | E83: ='Budget - Grantville'!E85+'Budget - Tyler'!E85 -> 0 | F83: ='Budget - Grantville'!F85+'Budget - Tyler'!F85 -> 0 | G83: ='Budget - Grantville'!G85+'Budget - Tyler'!G85 -> 0 | H83: ='Budget - Grantville'!H85+'Budget - Tyler'!H85 -> 0 | I83: ='Budget - Grantville'!I85+'Budget - Tyler'!I85 -> 0 | ... M83: ='Budget - Grantville'!M85+'Budget - Tyler'!M85 -> 0 | N83: =(((((((((((B83)+(C83))+(D83))+(E83))+(F83))+(G83))+(H83))+(I83))+(J83))+(K83))+(L83))+(M83) -> 0
A84: Total Staffing | B84: =SUM(B77:B83) -> 1200 | C84: =SUM(C77:C83) -> 1200 | D84: =SUM(D77:D83) -> 1200 | E84: =SUM(E77:E83) -> 1200 | F84: =SUM(F77:F83) -> 1200 | G84: =SUM(G77:G83) -> 1200 | H84: =SUM(H77:H83) -> 1200 | I84: =SUM(I77:I83) -> 1200 | ... M84: =SUM(M77:M83) -> 1200 | N84: =(((((((((((B84)+(C84))+(D84))+(E84))+(F84))+(G84))+(H84))+(I84))+(J84))+(K84))+(L84))+(M84) -> 14400 | O84: =SUM(O77:O83) -> 14035.85
A85: Taxes & Insurance
A86: Insurance - Prop & GL | B86: ='Budget - Grantville'!B88+'Budget - Tyler'!B88 -> 2754.4 | C86: ='Budget - Grantville'!C88+'Budget - Tyler'!C88 -> 2754.4 | D86: ='Budget - Grantville'!D88+'Budget - Tyler'!D88 -> 2754.4 | E86: ='Budget - Grantville'!E88+'Budget - Tyler'!E88 -> 2754.4 | F86: ='Budget - Grantville'!F88+'Budget - Tyler'!F88 -> 2754.4 | G86: ='Budget - Grantville'!G88+'Budget - Tyler'!G88 -> 2754.4 | H86: ='Budget - Grantville'!H88+'Budget - Tyler'!H88 -> 2754.4 | I86: ='Budget - Grantville'!I88+'Budget - Tyler'!I88 -> 2754.4 | ... M86: ='Budget - Grantville'!M88+'Budget - Tyler'!M88 -> 2754.4 | N86: =(((((((((((B86)+(C86))+(D86))+(E86))+(F86))+(G86))+(H86))+(I86))+(J86))+(K86))+(L86))+(M86) -> 33052.8 | O86: 16523.93
A87: Taxes-Property | B87: ='Budget - Grantville'!B89+'Budget - Tyler'!B89 -> 3728.73 | C87: ='Budget - Grantville'!C89+'Budget - Tyler'!C89 -> 3728.73 | D87: ='Budget - Grantville'!D89+'Budget - Tyler'!D89 -> 3728.73 | E87: ='Budget - Grantville'!E89+'Budget - Tyler'!E89 -> 3728.73 | F87: ='Budget - Grantville'!F89+'Budget - Tyler'!F89 -> 3728.73 | G87: ='Budget - Grantville'!G89+'Budget - Tyler'!G89 -> 3728.73 | H87: ='Budget - Grantville'!H89+'Budget - Tyler'!H89 -> 3728.73 | I87: ='Budget - Grantville'!I89+'Budget - Tyler'!I89 -> 3728.73 | ... M87: ='Budget - Grantville'!M89+'Budget - Tyler'!M89 -> 3728.73 | N87: =(((((((((((B87)+(C87))+(D87))+(E87))+(F87))+(G87))+(H87))+(I87))+(J87))+(K87))+(L87))+(M87) -> 44744.76 | O87: 41289.54
A88: Total Taxes & Insurance | B88: =SUM(B86:B87) -> 6483.13 | C88: =SUM(C86:C87) -> 6483.13 | D88: =SUM(D86:D87) -> 6483.13 | E88: =SUM(E86:E87) -> 6483.13 | F88: =SUM(F86:F87) -> 6483.13 | G88: =SUM(G86:G87) -> 6483.13 | H88: =SUM(H86:H87) -> 6483.13 | I88: =SUM(I86:I87) -> 6483.13 | ... M88: =SUM(M86:M87) -> 6483.13 | N88: =(((((((((((B88)+(C88))+(D88))+(E88))+(F88))+(G88))+(H88))+(I88))+(J88))+(K88))+(L88))+(M88) -> 77797.56 | O88: =SUM(O86:O87) -> 57813.47
A89: Utilities
A90: Telephone | B90: ='Budget - Grantville'!B92+'Budget - Tyler'!B92 -> 80 | C90: ='Budget - Grantville'!C92+'Budget - Tyler'!C92 -> 80 | D90: ='Budget - Grantville'!D92+'Budget - Tyler'!D92 -> 80 | E90: ='Budget - Grantville'!E92+'Budget - Tyler'!E92 -> 80 | F90: ='Budget - Grantville'!F92+'Budget - Tyler'!F92 -> 80 | G90: ='Budget - Grantville'!G92+'Budget - Tyler'!G92 -> 80 | H90: ='Budget - Grantville'!H92+'Budget - Tyler'!H92 -> 80 | I90: ='Budget - Grantville'!I92+'Budget - Tyler'!I92 -> 80 | ... M90: ='Budget - Grantville'!M92+'Budget - Tyler'!M92 -> 80 | N90: =(((((((((((B90)+(C90))+(D90))+(E90))+(F90))+(G90))+(H90))+(I90))+(J90))+(K90))+(L90))+(M90) -> 960 | O90: 1136.14
A91: Internet | B91: ='Budget - Grantville'!B93+'Budget - Tyler'!B93 -> 200 | C91: ='Budget - Grantville'!C93+'Budget - Tyler'!C93 -> 200 | D91: ='Budget - Grantville'!D93+'Budget - Tyler'!D93 -> 200 | E91: ='Budget - Grantville'!E93+'Budget - Tyler'!E93 -> 200 | F91: ='Budget - Grantville'!F93+'Budget - Tyler'!F93 -> 200 | G91: ='Budget - Grantville'!G93+'Budget - Tyler'!G93 -> 200 | H91: ='Budget - Grantville'!H93+'Budget - Tyler'!H93 -> 200 | I91: ='Budget - Grantville'!I93+'Budget - Tyler'!I93 -> 200 | ... M91: ='Budget - Grantville'!M93+'Budget - Tyler'!M93 -> 200 | N91: =(((((((((((B91)+(C91))+(D91))+(E91))+(F91))+(G91))+(H91))+(I91))+(J91))+(K91))+(L91))+(M91) -> 2400 | O91: 2034.68
A92: Electricity | B92: ='Budget - Grantville'!B94+'Budget - Tyler'!B94 -> 405 | C92: ='Budget - Grantville'!C94+'Budget - Tyler'!C94 -> 405 | D92: ='Budget - Grantville'!D94+'Budget - Tyler'!D94 -> 405 | E92: ='Budget - Grantville'!E94+'Budget - Tyler'!E94 -> 405 | F92: ='Budget - Grantville'!F94+'Budget - Tyler'!F94 -> 405 | G92: ='Budget - Grantville'!G94+'Budget - Tyler'!G94 -> 405 | H92: ='Budget - Grantville'!H94+'Budget - Tyler'!H94 -> 405 | I92: ='Budget - Grantville'!I94+'Budget - Tyler'!I94 -> 405 | ... M92: ='Budget - Grantville'!M94+'Budget - Tyler'!M94 -> 405 | N92: =(((((((((((B92)+(C92))+(D92))+(E92))+(F92))+(G92))+(H92))+(I92))+(J92))+(K92))+(L92))+(M92) -> 4860 | O92: 5014.11
A93: Water & Sewer | B93: ='Budget - Grantville'!B95+'Budget - Tyler'!B95 -> 400 | C93: ='Budget - Grantville'!C95+'Budget - Tyler'!C95 -> 400 | D93: ='Budget - Grantville'!D95+'Budget - Tyler'!D95 -> 400 | E93: ='Budget - Grantville'!E95+'Budget - Tyler'!E95 -> 400 | F93: ='Budget - Grantville'!F95+'Budget - Tyler'!F95 -> 400 | G93: ='Budget - Grantville'!G95+'Budget - Tyler'!G95 -> 400 | H93: ='Budget - Grantville'!H95+'Budget - Tyler'!H95 -> 400 | I93: ='Budget - Grantville'!I95+'Budget - Tyler'!I95 -> 400 | ... M93: ='Budget - Grantville'!M95+'Budget - Tyler'!M95 -> 400 | N93: =(((((((((((B93)+(C93))+(D93))+(E93))+(F93))+(G93))+(H93))+(I93))+(J93))+(K93))+(L93))+(M93) -> 4800 | O93: 5156.13
A94: Gas | B94: ='Budget - Grantville'!B96+'Budget - Tyler'!B96 -> 0 | C94: ='Budget - Grantville'!C96+'Budget - Tyler'!C96 -> 0 | D94: ='Budget - Grantville'!D96+'Budget - Tyler'!D96 -> 0 | E94: ='Budget - Grantville'!E96+'Budget - Tyler'!E96 -> 0 | F94: ='Budget - Grantville'!F96+'Budget - Tyler'!F96 -> 0 | G94: ='Budget - Grantville'!G96+'Budget - Tyler'!G96 -> 0 | H94: ='Budget - Grantville'!H96+'Budget - Tyler'!H96 -> 0 | I94: ='Budget - Grantville'!I96+'Budget - Tyler'!I96 -> 0 | ... M94: ='Budget - Grantville'!M96+'Budget - Tyler'!M96 -> 0 | N94: =(((((((((((B94)+(C94))+(D94))+(E94))+(F94))+(G94))+(H94))+(I94))+(J94))+(K94))+(L94))+(M94) -> 0 | O94: 65.61
A95: Stormwater | B95: ='Budget - Grantville'!B97+'Budget - Tyler'!B97 -> 0 | C95: ='Budget - Grantville'!C97+'Budget - Tyler'!C97 -> 0 | D95: ='Budget - Grantville'!D97+'Budget - Tyler'!D97 -> 0 | E95: ='Budget - Grantville'!E97+'Budget - Tyler'!E97 -> 0 | F95: ='Budget - Grantville'!F97+'Budget - Tyler'!F97 -> 0 | G95: ='Budget - Grantville'!G97+'Budget - Tyler'!G97 -> 0 | H95: ='Budget - Grantville'!H97+'Budget - Tyler'!H97 -> 0 | I95: ='Budget - Grantville'!I97+'Budget - Tyler'!I97 -> 0 | ... M95: ='Budget - Grantville'!M97+'Budget - Tyler'!M97 -> 0 | N95: =(((((((((((B95)+(C95))+(D95))+(E95))+(F95))+(G95))+(H95))+(I95))+(J95))+(K95))+(L95))+(M95) -> 0
A96: Trash/Disposal | B96: ='Budget - Grantville'!B98+'Budget - Tyler'!B98 -> 0 | C96: ='Budget - Grantville'!C98+'Budget - Tyler'!C98 -> 0 | D96: ='Budget - Grantville'!D98+'Budget - Tyler'!D98 -> 0 | E96: ='Budget - Grantville'!E98+'Budget - Tyler'!E98 -> 0 | F96: ='Budget - Grantville'!F98+'Budget - Tyler'!F98 -> 0 | G96: ='Budget - Grantville'!G98+'Budget - Tyler'!G98 -> 0 | H96: ='Budget - Grantville'!H98+'Budget - Tyler'!H98 -> 0 | I96: ='Budget - Grantville'!I98+'Budget - Tyler'!I98 -> 0 | ... M96: ='Budget - Grantville'!M98+'Budget - Tyler'!M98 -> 0 | N96: =(((((((((((B96)+(C96))+(D96))+(E96))+(F96))+(G96))+(H96))+(I96))+(J96))+(K96))+(L96))+(M96) -> 0 | O96: 973.4
A97: Total Utilities | B97: =SUM(B90:B96) -> 1085 | C97: =SUM(C90:C96) -> 1085 | D97: =SUM(D90:D96) -> 1085 | E97: =SUM(E90:E96) -> 1085 | F97: =SUM(F90:F96) -> 1085 | G97: =SUM(G90:G96) -> 1085 | H97: =SUM(H90:H96) -> 1085 | I97: =SUM(I90:I96) -> 1085 | ... M97: =SUM(M90:M96) -> 1085 | N97: =(((((((((((B97)+(C97))+(D97))+(E97))+(F97))+(G97))+(H97))+(I97))+(J97))+(K97))+(L97))+(M97) -> 13020 | O97: =SUM(O90:O96) -> 14380.07
A98: Total Expenses | B98: =B40+B47+B53+B64+B68+B75+B84+B88+B97 -> 14979.651 | C98: =C40+C47+C53+C64+C68+C75+C84+C88+C97 -> 14988.189 | D98: =D40+D47+D53+D64+D68+D75+D84+D88+D97 -> 15191.275 | E98: =E40+E47+E53+E64+E68+E75+E84+E88+E97 -> 15001.644 | F98: =F40+F47+F53+F64+F68+F75+F84+F88+F97 -> 15043.426 | G98: =G40+G47+G53+G64+G68+G75+G84+G88+G97 -> 15079.047 | H98: =H40+H47+H53+H64+H68+H75+H84+H88+H97 -> 15923.422 | I98: =I40+I47+I53+I64+I68+I75+I84+I88+I97 -> 15313.185 | ... M98: =M40+M47+M53+M64+M68+M75+M84+M88+M97 -> 15111.367 | N98: =(((((((((((B98)+(C98))+(D98))+(E98))+(F98))+(G98))+(H98))+(I98))+(J98))+(K98))+(L98))+(M98) -> 182202.09 | O98: =O40+O47+O53+O64+O68+O75+O84+O88+O97 -> 165836.57
A99: Net Operating Income | B99: =B31-B98 -> 11520.019 | C99: =C31-C98 -> 11448.135 | D99: =D31-D98 -> 11130.339 | E99: =E31-E98 -> 11491.012 | F99: =F31-F98 -> 11952.061 | G99: =G31-G98 -> 12346.873 | H99: =H31-H98 -> 12319.385 | I99: =I31-I98 -> 13633.528 | ... M99: =M31-M98 -> 13139.561 | N99: =(((((((((((B99)+(C99))+(D99))+(E99))+(F99))+(G99))+(H99))+(I99))+(J99))+(K99))+(L99))+(M99) -> 148668.5 | O99: =O31-O98 -> 124176.41
A101: Other Income/Expenses
A102: Bonus | B102: ='Budget - Grantville'!B104+'Budget - Tyler'!B104 -> 0 | C102: ='Budget - Grantville'!C104+'Budget - Tyler'!C104 -> 0 | D102: ='Budget - Grantville'!D104+'Budget - Tyler'!D104 -> 0 | E102: ='Budget - Grantville'!E104+'Budget - Tyler'!E104 -> 0 | F102: ='Budget - Grantville'!F104+'Budget - Tyler'!F104 -> 0 | G102: ='Budget - Grantville'!G104+'Budget - Tyler'!G104 -> 0 | H102: ='Budget - Grantville'!H104+'Budget - Tyler'!H104 -> 0 | I102: ='Budget - Grantville'!I104+'Budget - Tyler'!I104 -> 0 | ... M102: ='Budget - Grantville'!M104+'Budget - Tyler'!M104 -> 0 | N102: =(((((((((((B102)+(C102))+(D102))+(E102))+(F102))+(G102))+(H102))+(I102))+(J102))+(K102))+(L102))+(M102) -> 0 | O102: 3300
A103: Travel Meals/Hotels | B103: ='Budget - Grantville'!B105+'Budget - Tyler'!B105 -> 0 | C103: ='Budget - Grantville'!C105+'Budget - Tyler'!C105 -> 0 | D103: ='Budget - Grantville'!D105+'Budget - Tyler'!D105 -> 0 | E103: ='Budget - Grantville'!E105+'Budget - Tyler'!E105 -> 0 | F103: ='Budget - Grantville'!F105+'Budget - Tyler'!F105 -> 0 | G103: ='Budget - Grantville'!G105+'Budget - Tyler'!G105 -> 0 | H103: ='Budget - Grantville'!H105+'Budget - Tyler'!H105 -> 0 | I103: ='Budget - Grantville'!I105+'Budget - Tyler'!I105 -> 0 | ... M103: ='Budget - Grantville'!M105+'Budget - Tyler'!M105 -> 0 | N103: =(((((((((((B103)+(C103))+(D103))+(E103))+(F103))+(G103))+(H103))+(I103))+(J103))+(K103))+(L103))+(M103) -> 0 | O103: =103.08-98.29 -> 4.79
...

Sheet Budget - Tyler
B1: Topeka Self Storage - Tyler
B2: Budget
B3: January - December 2026
B5: 46023 | C5: 46054 | D5: 46082 | E5: 46113 | F5: 46143 | G5: 46174 | H5: 46204 | I5: 46235 | J5: 46266 | K5: 46296 | L5: 46327 | M5: 46357
A6: Rented | B6: 3 | C6: 3 | D6: 3 | E6: 5 | F6: 5 | G6: 5 | H6: 8 | I6: 8 | J6: 5 | K6: 5 | L6: 5 | M6: 5
A7: Vacated | B7: =B8*0.06 -> 4.26 | C7: =B8*0.07 -> 4.97 | D7: =C8*0.07 -> 4.8321 | E7: =D8*0.07 -> 4.703853 | F7: =E8*0.07 -> 4.7245833 | G7: =F8*0.07 -> 4.7438625 | H7: =G8*0.07 -> 4.7617921 | I7: =H8*0.07 -> 4.9884666 | J7: =I8*0.07 -> 5.199274 | ... M7: =L8*0.07 -> 5.1602874
A8: Net occupied | B8: 71 | C8: =B8+C6-C7 -> 69.03 | D8: =C8+D6-D7 -> 67.1979 | E8: =D8+E6-E7 -> 67.494047 | F8: =E8+F6-F7 -> 67.769464 | G8: =F8+G6-G7 -> 68.025601 | H8: =G8+H6-H7 -> 71.263809 | I8: =H8+I6-I7 -> 74.275343 | J8: =I8+J6-J7 -> 74.076069 | ... M8: =L8+M6-M7 -> 73.558104
A9: % occupied | B9: =B8/82 -> 0.86585366 | C9: =C8/82 -> 0.84182927 | D9: =D8/82 -> 0.81948659 | E9: =E8/82 -> 0.82309813 | F9: =F8/82 -> 0.82645687 | G9: =G8/82 -> 0.8295805 | H9: =H8/82 -> 0.86907084 | I9: =I8/82 -> 0.90579686 | ... M9: =M8/82 -> 0.89705005
B10: 46023 | C10: 46054 | D10: 46082 | E10: 46113 | F10: 46143 | G10: 46174 | H10: 46204 | I10: 46235 | J10: 46266 | K10: 46296 | L10: 46327 | M10: 46357 | N10: Total
A11: Revenue Projection
A12: Rent Income | B12: =(8334/73)*B8*0.97 -> 7862.5011 | C12: =(8334/73)*C8*0.97 -> 7644.3444 | D12: =(8334/73)*D8*0.97 -> 7441.4586 | E12: =(8334/73)*E8*0.97 -> 7474.2538 | F12: =(8334/73)*F8*0.97 -> 7504.7533 | G12: =(8334/73)*G8*0.97 -> 7533.1178 | H12: =(8334/73)*H8*0.97 -> 7891.7152 | I12: =(8334/73)*I8*0.97 -> 8225.2107 | ... M12: =(8334/73)*M8*0.97 -> 8145.7842 | N12: =SUM(B12:M12) -> 94272.437
A13: Other Rent Income | N13: =SUM(B13:M13) -> 0
A14: Other Rent Income | N14: =SUM(B14:M14) -> 0
A15: Total Rental Income | B15: =SUM(B12:B14) -> 7862.5011 | C15: =SUM(C12:C14) -> 7644.3444 | D15: =SUM(D12:D14) -> 7441.4586 | E15: =SUM(E12:E14) -> 7474.2538 | F15: =SUM(F12:F14) -> 7504.7533 | G15: =SUM(G12:G14) -> 7533.1178 | H15: =SUM(H12:H14) -> 7891.7152 | I15: =SUM(I12:I14) -> 8225.2107 | ... M15: =SUM(M12:M14) -> 8145.7842 | N15: =(((((((((((B15)+(C15))+(D15))+(E15))+(F15))+(G15))+(H15))+(I15))+(J15))+(K15))+(L15))+(M15) -> 94272.437
A16: Fee Income
A17: Admin Fees | B17: =B6*20 -> 60 | C17: =C6*20 -> 60 | D17: =D6*20 -> 60 | E17: =E6*20 -> 100 | F17: =F6*20 -> 100 | G17: =G6*20 -> 100 | H17: =H6*20 -> 160 | I17: =I6*20 -> 160 | ... M17: =M6*20 -> 100 | N17: =SUM(B17:M17) -> 1200
A18: Late Fee Income | B18: =B12*0.03 -> 235.87503 | C18: =C12*0.03 -> 229.33033 | D18: =D12*0.03 -> 223.24376 | E18: =E12*0.03 -> 224.22761 | F18: =F12*0.03 -> 225.1426 | G18: =G12*0.03 -> 225.99353 | H18: =H12*0.03 -> 236.75146 | I18: =I12*0.03 -> 246.75632 | ... M18: =M12*0.03 -> 244.37352 | N18: =SUM(B18:M18) -> 2828.1731
A19: Convenience Fee | B19: =5*(B8*0.05) -> 17.75 | C19: =5*(C8*0.05) -> 17.2575 | D19: =5*(D8*0.05) -> 16.799475 | E19: =5*(E8*0.05) -> 16.873512 | F19: =5*(F8*0.05) -> 16.942366 | G19: =5*(G8*0.05) -> 17.0064 | H19: =5*(H8*0.05) -> 17.815952 | I19: =5*(I8*0.05) -> 18.568836 | ... M19: =5*(M8*0.05) -> 18.389526 | N19: =SUM(B19:M19) -> 212.82487
A20: General Fee Income | N20: =SUM(B20:M20) -> 0
A21: Other Fee | N21: =SUM(B21:M21) -> 0
A22: Total Fee Income | B22: =SUM(B17:B21) -> 313.62503 | C22: =SUM(C17:C21) -> 306.58783 | D22: =SUM(D17:D21) -> 300.04323 | E22: =SUM(E17:E21) -> 341.10113 | F22: =SUM(F17:F21) -> 342.08496 | G22: =SUM(G17:G21) -> 342.99993 | H22: =SUM(H17:H21) -> 414.56741 | I22: =SUM(I17:I21) -> 425.32516 | ... M22: =SUM(M17:M21) -> 362.76305 | N22: =(((((((((((B22)+(C22))+(D22))+(E22))+(F22))+(G22))+(H22))+(I22))+(J22))+(K22))+(L22))+(M22) -> 4240.998
A23: Ancillary Income
A24: Merchandise Income | B24: 0 | C24: 0 | D24: 0 | E24: 0 | F24: 0 | G24: 0 | H24: 0 | I24: 0 | J24: 0 | K24: 0 | L24: 0 | M24: 0 | N24: =SUM(B24:M24) -> 0
A25: Tenant Protection | B25: =B8*0.91*5 -> 323.05 | C25: =C8*0.91*5 -> 314.0865 | D25: =D8*0.91*5 -> 305.75045 | E25: =E8*0.91*5 -> 307.09791 | F25: =F8*0.91*5 -> 308.35106 | G25: =G8*0.91*5 -> 309.51649 | H25: =H8*0.91*5 -> 324.25033 | I25: =I8*0.91*5 -> 337.95281 | ... M25: =M8*0.91*5 -> 334.68937 | N25: =SUM(B25:M25) -> 3873.4126
A26: Truck Rentals | N26: =SUM(B26:M26) -> 0
A27: Propane Sales | N27: =SUM(B27:M27) -> 0
A28: Other Income Sources | N28: =SUM(B28:M28) -> 0
A29: Other Income Sources | N29: =SUM(B29:M29) -> 0
A30: Total Ancillary Income | B30: =SUM(B24:B29) -> 323.05 | C30: =SUM(C24:C29) -> 314.0865 | D30: =SUM(D24:D29) -> 305.75045 | E30: =SUM(E24:E29) -> 307.09791 | F30: =SUM(F24:F29) -> 308.35106 | G30: =SUM(G24:G29) -> 309.51649 | H30: =SUM(H24:H29) -> 324.25033 | I30: =SUM(I24:I29) -> 337.95281 | ... M30: =SUM(M24:M29) -> 334.68937 | N30: =(((((((((((B30)+(C30))+(D30))+(E30))+(F30))+(G30))+(H30))+(I30))+(J30))+(K30))+(L30))+(M30) -> 3873.4126
A31: Total Revenue | B31: =B15+B22+B30 -> 8499.1761 | C31: =C15+C22+C30 -> 8265.0187 | D31: =D15+D22+D30 -> 8047.2523 | E31: =E15+E22+E30 -> 8122.4528 | F31: =F15+F22+F30 -> 8155.1893 | G31: =G15+G22+G30 -> 8185.6342 | H31: =H15+H22+H30 -> 8630.5329 | I31: =I15+I22+I30 -> 8988.4887 | ... M31: =M15+M22+M30 -> 8843.2366 | N31: =SUM(B31:M31) -> 102386.85
A33: Expense Projection
A34: Advertising/Marketing
A35: PPC (payperclick) | B35: 300 | C35: =B35 -> 300 | D35: =C35 -> 300 | E35: =D35 -> 300 | F35: =E35 -> 300 | G35: =F35 -> 300 | H35: =G35 -> 300 | I35: =H35 -> 300 | J35: =I35 -> 300 | ... M35: =L35 -> 300 | N35: =(((((((((((B35)+(C35))+(D35))+(E35))+(F35))+(G35))+(H35))+(I35))+(J35))+(K35))+(L35))+(M35) -> 3600
A36: Print Materials | B36: 0 | C36: 0 | D36: 100 | E36: 0 | F36: =0 -> 0 | G36: =0 -> 0 | H36: 100 | I36: =0 -> 0 | J36: =0 -> 0 | K36: =0 -> 0 | L36: 100 | M36: =0 -> 0 | N36: =(((((((((((B36)+(C36))+(D36))+(E36))+(F36))+(G36))+(H36))+(I36))+(J36))+(K36))+(L36))+(M36) -> 300
A37: Reputation & Social | B37: 0 | C37: =B37 -> 0 | D37: =C37 -> 0 | E37: =D37 -> 0 | F37: =E37 -> 0 | G37: =F37 -> 0 | H37: =G37 -> 0 | I37: =H37 -> 0 | J37: =I37 -> 0 | ... M37: =L37 -> 0 | N37: =(((((((((((B37)+(C37))+(D37))+(E37))+(F37))+(G37))+(H37))+(I37))+(J37))+(K37))+(L37))+(M37) -> 0
A38: Website | B38: 300 | C38: =B38 -> 300 | D38: =C38 -> 300 | E38: =D38 -> 300 | F38: =E38 -> 300 | G38: =F38 -> 300 | H38: =G38 -> 300 | I38: =H38 -> 300 | J38: =I38 -> 300 | ... M38: =L38 -> 300 | N38: =(((((((((((B38)+(C38))+(D38))+(E38))+(F38))+(G38))+(H38))+(I38))+(J38))+(K38))+(L38))+(M38) -> 3600
A39: Sparefoot | B39: 0 | C39: =B39 -> 0 | D39: =C39 -> 0 | E39: =D39 -> 0 | F39: =E39 -> 0 | G39: =F39 -> 0 | H39: =G39 -> 0 | I39: =H39 -> 0 | J39: =I39 -> 0 | ... M39: =L39 -> 0 | N39: =(((((((((((B39)+(C39))+(D39))+(E39))+(F39))+(G39))+(H39))+(I39))+(J39))+(K39))+(L39))+(M39) -> 0
A40: Advertising/Marketing | B40: =SUM(B35:B39) -> 600 | C40: =SUM(C35:C39) -> 600 | D40: =SUM(D35:D39) -> 700 | E40: =SUM(E35:E39) -> 600 | F40: =SUM(F35:F39) -> 600 | G40: =SUM(G35:G39) -> 600 | H40: =SUM(H35:H39) -> 700 | I40: =SUM(I35:I39) -> 600 | ... M40: =SUM(M35:M39) -> 600 | N40: =(((((((((((B40)+(C40))+(D40))+(E40))+(F40))+(G40))+(H40))+(I40))+(J40))+(K40))+(L40))+(M40) -> 7500
A41: Legal & Professional Fees | N41: =(((((((((((B41)+(C41))+(D41))+(E41))+(F41))+(G41))+(H41))+(I41))+(J41))+(K41))+(L41))+(M41) -> 0
A42: Auction Expenses | B42: 100 | C42: 100 | D42: 100 | E42: 100 | F42: 100 | G42: 100 | H42: 100 | I42: 100 | J42: 100 | K42: 100 | L42: 100 | M42: 100 | N42: =(((((((((((B42)+(C42))+(D42))+(E42))+(F42))+(G42))+(H42))+(I42))+(J42))+(K42))+(L42))+(M42) -> 1200
A43: Management Services | B43: =IF(B31*0.06<1000,1000,B31*0.06) -> 1000 | C43: =IF(C31*0.06<1000,1000,C31*0.06) -> 1000 | D43: =IF(D31*0.06<1000,1000,D31*0.06) -> 1000 | E43: =IF(E31*0.06<1000,1000,E31*0.06) -> 1000 | F43: =IF(F31*0.06<1000,1000,F31*0.06) -> 1000 | G43: =IF(G31*0.06<1000,1000,G31*0.06) -> 1000 | H43: =IF(H31*0.06<1000,1000,H31*0.06) -> 1000 | I43: =IF(I31*0.06<1000,1000,I31*0.06) -> 1000 | ... M43: =IF(M31*0.06<1000,1000,M31*0.06) -> 1000 | N43: =(((((((((((B43)+(C43))+(D43))+(E43))+(F43))+(G43))+(H43))+(I43))+(J43))+(K43))+(L43))+(M43) -> 12000
A44: Call Center | B44: 0 | C44: 0 | D44: 0 | E44: 0 | F44: 0 | G44: 0 | H44: 0 | I44: 0 | J44: 0 | K44: 0 | L44: 0 | M44: 0 | N44: =(((((((((((B44)+(C44))+(D44))+(E44))+(F44))+(G44))+(H44))+(I44))+(J44))+(K44))+(L44))+(M44) -> 0
A45: Legal Fees | B45: 0 | C45: 0 | D45: 0 | E45: 0 | F45: 0 | G45: 0 | H45: 150 | I45: 75 | J45: 0 | K45: 0 | L45: 0 | M45: 0 | N45: =(((((((((((B45)+(C45))+(D45))+(E45))+(F45))+(G45))+(H45))+(I45))+(J45))+(K45))+(L45))+(M45) -> 225
A46: Accounting Fees | B46: 0 | C46: 0 | D46: 0 | E46: 0 | F46: 0 | G46: 0 | H46: 150 | I46: 0 | J46: 0 | K46: 0 | L46: 0 | M46: 0 | N46: =(((((((((((B46)+(C46))+(D46))+(E46))+(F46))+(G46))+(H46))+(I46))+(J46))+(K46))+(L46))+(M46) -> 150
A47: Total Legal & Professional Fees | B47: =SUM(B42:B46) -> 1100 | C47: =SUM(C42:C46) -> 1100 | D47: =SUM(D42:D46) -> 1100 | E47: =SUM(E42:E46) -> 1100 | F47: =SUM(F42:F46) -> 1100 | G47: =SUM(G42:G46) -> 1100 | H47: =SUM(H42:H46) -> 1400 | I47: =SUM(I42:I46) -> 1175 | ... M47: =SUM(M42:M46) -> 1100 | N47: =(((((((((((B47)+(C47))+(D47))+(E47))+(F47))+(G47))+(H47))+(I47))+(J47))+(K47))+(L47))+(M47) -> 13575
A48: Office/Site
A49: Cost of Merchandise Sold | B49: =B24*0.4 -> 0 | C49: =C24*0.4 -> 0 | D49: =D24*0.4 -> 0 | E49: =E24*0.4 -> 0 | F49: =F24*0.4 -> 0 | G49: =G24*0.4 -> 0 | H49: =H24*0.4 -> 0 | I49: =I24*0.4 -> 0 | ... M49: =M24*0.4 -> 0 | N49: =(((((((((((B49)+(C49))+(D49))+(E49))+(F49))+(G49))+(H49))+(I49))+(J49))+(K49))+(L49))+(M49) -> 0
A50: Site Supplies | B50: 50 | C50: 50 | D50: 50 | E50: 50 | F50: 50 | G50: 50 | H50: 50 | I50: 50 | J50: 50 | K50: 50 | L50: 50 | M50: 50 | N50: =(((((((((((B50)+(C50))+(D50))+(E50))+(F50))+(G50))+(H50))+(I50))+(J50))+(K50))+(L50))+(M50) -> 600
A51: Office Supplies | B51: 50 | C51: 50 | D51: 50 | E51: 50 | F51: 50 | G51: 50 | H51: 50 | I51: 50 | J51: 50 | K51: 50 | L51: 50 | M51: 50 | N51: =(((((((((((B51)+(C51))+(D51))+(E51))+(F51))+(G51))+(H51))+(I51))+(J51))+(K51))+(L51))+(M51) -> 600
A52: Business Licenses
A53: Site Supplies
A54: Office Supplies
A55: Total Office/Site | B55: =SUM(B49:B54) -> 100 | C55: =SUM(C49:C54) -> 100 | D55: =SUM(D49:D54) -> 100 | E55: =SUM(E49:E54) -> 100 | F55: =SUM(F49:F54) -> 100 | G55: =SUM(G49:G54) -> 100 | H55: =SUM(H49:H54) -> 100 | I55: =SUM(I49:I54) -> 100 | ... M55: =SUM(M49:M54) -> 100 | N55: =(((((((((((B55)+(C55))+(D55))+(E55))+(F55))+(G55))+(H55))+(I55))+(J55))+(K55))+(L55))+(M55) -> 1200
A56: Repairs and Maintenance
A57: Lawn/Snow | B57: 300 | C57: 300 | D57: 300 | E57: 300 | F57: 300 | G57: 300 | H57: 300 | I57: 300 | J57: 300 | K57: 300 | L57: 300 | M57: 300 | N57: =(((((((((((B57)+(C57))+(D57))+(E57))+(F57))+(G57))+(H57))+(I57))+(J57))+(K57))+(L57))+(M57) -> 3600
A58: Elevator | N58: =(((((((((((B58)+(C58))+(D58))+(E58))+(F58))+(G58))+(H58))+(I58))+(J58))+(K58))+(L58))+(M58) -> 0
A59: Gate & Fence
A60: Unit Doors
A61: Security System
A62: HVAC
A63: Pest Control | N63: =(((((((((((B63)+(C63))+(D63))+(E63))+(F63))+(G63))+(H63))+(I63))+(J63))+(K63))+(L63))+(M63) -> 0
A64: Site | B64: 300 | C64: 300 | D64: 300 | E64: 300 | F64: 300 | G64: 300 | H64: 300 | I64: 300 | J64: 300 | K64: 300 | L64: 300 | M64: 300 | N64: =(((((((((((B64)+(C64))+(D64))+(E64))+(F64))+(G64))+(H64))+(I64))+(J64))+(K64))+(L64))+(M64) -> 3600
A65: Trash Hauling
A66: Total Repairs and Maintenance | B66: =SUM(B57:B65) -> 600 | C66: =SUM(C57:C65) -> 600 | D66: =SUM(D57:D65) -> 600 | E66: =SUM(E57:E65) -> 600 | F66: =SUM(F57:F65) -> 600 | G66: =SUM(G57:G65) -> 600 | H66: =SUM(H57:H65) -> 600 | I66: =SUM(I57:I65) -> 600 | ... M66: =SUM(M57:M65) -> 600 | N66: =(((((((((((B66)+(C66))+(D66))+(E66))+(F66))+(G66))+(H66))+(I66))+(J66))+(K66))+(L66))+(M66) -> 7200
A67: Service Charges
A68: Bank Service Charges | B68: 0 | C68: =B68 -> 0 | D68: =C68 -> 0 | E68: =D68 -> 0 | F68: =E68 -> 0 | G68: =F68 -> 0 | H68: =G68 -> 0 | I68: =H68 -> 0 | J68: =I68 -> 0 | ... M68: =L68 -> 0 | N68: =(((((((((((B68)+(C68))+(D68))+(E68))+(F68))+(G68))+(H68))+(I68))+(J68))+(K68))+(L68))+(M68) -> 0
A69: Credit Card Service Fees | B69: =B31*0.027 -> 229.47776 | C69: =C31*0.027 -> 223.15551 | D69: =D31*0.027 -> 217.27581 | E69: =E31*0.027 -> 219.30623 | F69: =F31*0.027 -> 220.19011 | G69: =G31*0.027 -> 221.01212 | H69: =H31*0.027 -> 233.02439 | I69: =I31*0.027 -> 242.68919 | ... M69: =M31*0.027 -> 238.76739 | N69: =N31*0.02 -> 2047.737
A70: Total Service Charges | B70: =SUM(B68:B69) -> 229.47776 | C70: =SUM(C68:C69) -> 223.15551 | D70: =SUM(D68:D69) -> 217.27581 | E70: =SUM(E68:E69) -> 219.30623 | F70: =SUM(F68:F69) -> 220.19011 | G70: =SUM(G68:G69) -> 221.01212 | H70: =SUM(H68:H69) -> 233.02439 | I70: =SUM(I68:I69) -> 242.68919 | ... M70: =SUM(M68:M69) -> 238.76739 | N70: =(((((((((((B70)+(C70))+(D70))+(E70))+(F70))+(G70))+(H70))+(I70))+(J70))+(K70))+(L70))+(M70) -> 2764.4449
A71: Software
A72: Gate Software | N72: =(((((((((((B72)+(C72))+(D72))+(E72))+(F72))+(G72))+(H72))+(I72))+(J72))+(K72))+(L72))+(M72) -> 0
A73: Collection Software | N73: =(((((((((((B73)+(C73))+(D73))+(E73))+(F73))+(G73))+(H73))+(I73))+(J73))+(K73))+(L73))+(M73) -> 0
A74: Accounting/BillPay Software | B74: 80 | C74: 80 | D74: 80 | E74: 80 | F74: 80 | G74: 80 | H74: 80 | I74: 80 | J74: 80 | K74: 80 | L74: 80 | M74: 80 | N74: =(((((((((((B74)+(C74))+(D74))+(E74))+(F74))+(G74))+(H74))+(I74))+(J74))+(K74))+(L74))+(M74) -> 960
A75: Other Software (Swivel) | B75: 63 | C75: 63 | D75: 63 | E75: 63 | F75: 63 | G75: 63 | H75: 63 | I75: 63 | J75: 63 | K75: 63 | L75: 63 | M75: 63 | N75: =(((((((((((B75)+(C75))+(D75))+(E75))+(F75))+(G75))+(H75))+(I75))+(J75))+(K75))+(L75))+(M75) -> 756
A76: Storage Software | B76: 95 | C76: =B76 -> 95 | D76: =C76 -> 95 | E76: =D76 -> 95 | F76: =E76 -> 95 | G76: =F76 -> 95 | H76: =G76 -> 95 | I76: =H76 -> 95 | J76: =I76 -> 95 | ... M76: =L76 -> 95 | N76: =(((((((((((B76)+(C76))+(D76))+(E76))+(F76))+(G76))+(H76))+(I76))+(J76))+(K76))+(L76))+(M76) -> 1140
A77: Total Software | B77: =SUM(B72:B76) -> 238 | C77: =SUM(C72:C76) -> 238 | D77: =SUM(D72:D76) -> 238 | E77: =SUM(E72:E76) -> 238 | F77: =SUM(F72:F76) -> 238 | G77: =SUM(G72:G76) -> 238 | H77: =SUM(H72:H76) -> 238 | I77: =SUM(I72:I76) -> 238 | ... M77: =SUM(M72:M76) -> 238 | N77: =(((((((((((B77)+(C77))+(D77))+(E77))+(F77))+(G77))+(H77))+(I77))+(J77))+(K77))+(L77))+(M77) -> 2856
A78: Staffing
A79: Mileage | N79: =(((((((((((B79)+(C79))+(D79))+(E79))+(F79))+(G79))+(H79))+(I79))+(J79))+(K79))+(L79))+(M79) -> 0
A80: Payroll Processing | N80: =(((((((((((B80)+(C80))+(D80))+(E80))+(F80))+(G80))+(H80))+(I80))+(J80))+(K80))+(L80))+(M80) -> 0
A81: Payroll Taxes | N81: =(((((((((((B81)+(C81))+(D81))+(E81))+(F81))+(G81))+(H81))+(I81))+(J81))+(K81))+(L81))+(M81) -> 0
A82: Staff Costs | N82: =(((((((((((B82)+(C82))+(D82))+(E82))+(F82))+(G82))+(H82))+(I82))+(J82))+(K82))+(L82))+(M82) -> 0
A83: Health Insurance | N83: =(((((((((((B83)+(C83))+(D83))+(E83))+(F83))+(G83))+(H83))+(I83))+(J83))+(K83))+(L83))+(M83) -> 0
A84: Salary/Wages | B84: 600 | C84: =B84 -> 600 | D84: =C84 -> 600 | E84: =D84 -> 600 | F84: =E84 -> 600 | G84: =F84 -> 600 | H84: =G84 -> 600 | I84: =H84 -> 600 | J84: =I84 -> 600 | ... M84: =L84 -> 600 | N84: =(((((((((((B84)+(C84))+(D84))+(E84))+(F84))+(G84))+(H84))+(I84))+(J84))+(K84))+(L84))+(M84) -> 7200
A85: Workers Comp | N85: =(((((((((((B85)+(C85))+(D85))+(E85))+(F85))+(G85))+(H85))+(I85))+(J85))+(K85))+(L85))+(M85) -> 0
A86: Total Staffing | B86: =SUM(B79:B85) -> 600 | C86: =SUM(C79:C85) -> 600 | D86: =SUM(D79:D85) -> 600 | E86: =SUM(E79:E85) -> 600 | F86: =SUM(F79:F85) -> 600 | G86: =SUM(G79:G85) -> 600 | H86: =SUM(H79:H85) -> 600 | I86: =SUM(I79:I85) -> 600 | ... M86: =SUM(M79:M85) -> 600 | N86: =(((((((((((B86)+(C86))+(D86))+(E86))+(F86))+(G86))+(H86))+(I86))+(J86))+(K86))+(L86))+(M86) -> 7200
A87: Taxes & Insurance
A88: Insurance - Prop & GL | B88: 1453.43 | C88: 1453.43 | D88: 1453.43 | E88: 1453.43 | F88: 1453.43 | G88: 1453.43 | H88: 1453.43 | I88: 1453.43 | J88: 1453.43 | K88: 1453.43 | L88: 1453.43 | M88: 1453.43 | N88: =(((((((((((B88)+(C88))+(D88))+(E88))+(F88))+(G88))+(H88))+(I88))+(J88))+(K88))+(L88))+(M88) -> 17441.16
A89: Taxes-Property | B89: =3728.73/2 -> 1864.365 | C89: =3728.73/2 -> 1864.365 | D89: =3728.73/2 -> 1864.365 | E89: =3728.73/2 -> 1864.365 | F89: =3728.73/2 -> 1864.365 | G89: =3728.73/2 -> 1864.365 | H89: =3728.73/2 -> 1864.365 | I89: =3728.73/2 -> 1864.365 | ... M89: =3728.73/2 -> 1864.365 | N89: =(((((((((((B89)+(C89))+(D89))+(E89))+(F89))+(G89))+(H89))+(I89))+(J89))+(K89))+(L89))+(M89) -> 22372.38
A90: Total Taxes & Insurance | B90: =SUM(B88:B89) -> 3317.795 | C90: =SUM(C88:C89) -> 3317.795 | D90: =SUM(D88:D89) -> 3317.795 | E90: =SUM(E88:E89) -> 3317.795 | F90: =SUM(F88:F89) -> 3317.795 | G90: =SUM(G88:G89) -> 3317.795 | H90: =SUM(H88:H89) -> 3317.795 | I90: =SUM(I88:I89) -> 3317.795 | ... M90: =SUM(M88:M89) -> 3317.795 | N90: =(((((((((((B90)+(C90))+(D90))+(E90))+(F90))+(G90))+(H90))+(I90))+(J90))+(K90))+(L90))+(M90) -> 39813.54
A91: Utilities
A92: Telephone | B92: 40 | C92: 40 | D92: 40 | E92: 40 | F92: 40 | G92: 40 | H92: 40 | I92: 40 | J92: 40 | K92: 40 | L92: 40 | M92: 40 | N92: =(((((((((((B92)+(C92))+(D92))+(E92))+(F92))+(G92))+(H92))+(I92))+(J92))+(K92))+(L92))+(M92) -> 480
A93: Internet | B93: 100 | C93: 100 | D93: 100 | E93: 100 | F93: 100 | G93: 100 | H93: 100 | I93: 100 | J93: 100 | K93: 100 | L93: 100 | M93: 100 | N93: =(((((((((((B93)+(C93))+(D93))+(E93))+(F93))+(G93))+(H93))+(I93))+(J93))+(K93))+(L93))+(M93) -> 1200
A94: Electricity | B94: 175 | C94: 175 | D94: 175 | E94: 175 | F94: 175 | G94: 175 | H94: 175 | I94: 175 | J94: 175 | K94: 175 | L94: 175 | M94: 175 | N94: =(((((((((((B94)+(C94))+(D94))+(E94))+(F94))+(G94))+(H94))+(I94))+(J94))+(K94))+(L94))+(M94) -> 2100
A95: Water & Sewer | B95: 200 | C95: 200 | D95: 200 | E95: 200 | F95: 200 | G95: 200 | H95: 200 | I95: 200 | J95: 200 | K95: 200 | L95: 200 | M95: 200 | N95: =(((((((((((B95)+(C95))+(D95))+(E95))+(F95))+(G95))+(H95))+(I95))+(J95))+(K95))+(L95))+(M95) -> 2400
A96: Gas | N96: =(((((((((((B96)+(C96))+(D96))+(E96))+(F96))+(G96))+(H96))+(I96))+(J96))+(K96))+(L96))+(M96) -> 0
A97: Stormwater | N97: =(((((((((((B97)+(C97))+(D97))+(E97))+(F97))+(G97))+(H97))+(I97))+(J97))+(K97))+(L97))+(M97) -> 0
A98: Trash/Disposal | N98: =(((((((((((B98)+(C98))+(D98))+(E98))+(F98))+(G98))+(H98))+(I98))+(J98))+(K98))+(L98))+(M98) -> 0
A99: Total Utilities | B99: =SUM(B92:B98) -> 515 | C99: =SUM(C92:C98) -> 515 | D99: =SUM(D92:D98) -> 515 | E99: =SUM(E92:E98) -> 515 | F99: =SUM(F92:F98) -> 515 | G99: =SUM(G92:G98) -> 515 | H99: =SUM(H92:H98) -> 515 | I99: =SUM(I92:I98) -> 515 | ... M99: =SUM(M92:M98) -> 515 | N99: =(((((((((((B99)+(C99))+(D99))+(E99))+(F99))+(G99))+(H99))+(I99))+(J99))+(K99))+(L99))+(M99) -> 6180
A100: Total Expenses | B100: =B40+B47+B55+B66+B70+B77+B86+B90+B99 -> 7300.2728 | C100: =C40+C47+C55+C66+C70+C77+C86+C90+C99 -> 7293.9505 | D100: =D40+D47+D55+D66+D70+D77+D86+D90+D99 -> 7388.0708 | E100: =E40+E47+E55+E66+E70+E77+E86+E90+E99 -> 7290.1012 | F100: =F40+F47+F55+F66+F70+F77+F86+F90+F99 -> 7290.9851 | G100: =G40+G47+G55+G66+G70+G77+G86+G90+G99 -> 7291.8071 | H100: =H40+H47+H55+H66+H70+H77+H86+H90+H99 -> 7703.8194 | I100: =I40+I47+I55+I66+I70+I77+I86+I90+I99 -> 7388.4842 | ... M100: =M40+M47+M55+M66+M70+M77+M86+M90+M99 -> 7309.5624 | N100: =(((((((((((B100)+(C100))+(D100))+(E100))+(F100))+(G100))+(H100))+(I100))+(J100))+(K100))+(L100))+(M100) -> 88288.985
A101: Net Operating Income | B101: =B31-B100 -> 1198.9034 | C101: =C31-C100 -> 971.0682 | D101: =D31-D100 -> 659.18149 | E101: =E31-E100 -> 832.35159 | F101: =F31-F100 -> 864.20419 | G101: =G31-G100 -> 893.8271 | H101: =H31-H100 -> 926.71353 | I101: =I31-I100 -> 1600.0045 | ... M101: =M31-M100 -> 1533.6742 | N101: =(((((((((((B101)+(C101))+(D101))+(E101))+(F101))+(G101))+(H101))+(I101))+(J101))+(K101))+(L101))+(M101) -> 14097.863
A103: Other Income/Expenses
...

Sheet Budget - Grantville
B1: Topeka Self Storage - Grantville
B2: Budget
B3: January - December 2026
B5: 46023 | C5: 46054 | D5: 46082 | E5: 46113 | F5: 46143 | G5: 46174 | H5: 46204 | I5: 46235 | J5: 46266 | K5: 46296 | L5: 46327 | M5: 46357
A6: Rented | B6: 5 | C6: 8 | D6: 8 | E6: 8 | F6: 10 | G6: 10 | H6: 10 | I6: 10 | J6: 7 | K6: 7 | L6: 7 | M6: 7
A7: Vacated | B7: =B8*0.06 -> 6.3 | C7: =B8*0.07 -> 7.35 | D7: =C8*0.07 -> 7.3955 | E7: =D8*0.07 -> 7.437815 | F7: =E8*0.07 -> 7.477168 | G7: =F8*0.07 -> 7.6537662 | H7: =G8*0.07 -> 7.8180026 | I7: =H8*0.07 -> 7.9707424 | J7: =I8*0.07 -> 8.1127904 | ... L7: =K8*0.07 -> 7.9624524 | M7: =L8*0.06 -> 6.7672121
A8: Net occupied | B8: 105 | C8: =B8+C6-C7 -> 105.65 | D8: =C8+D6-D7 -> 106.2545 | E8: =D8+E6-E7 -> 106.81669 | F8: =E8+F6-F7 -> 109.33952 | G8: =F8+G6-G7 -> 111.68575 | H8: =G8+H6-H7 -> 113.86775 | I8: =H8+I6-I7 -> 115.89701 | J8: =I8+J6-J7 -> 114.78422 | ... M8: =L8+M6-M7 -> 113.01966
A9: % occupied | B9: =B8/126 -> 0.83333333 | C9: =C8/126 -> 0.83849206 | D9: =D8/126 -> 0.84328968 | E9: =E8/126 -> 0.84775147 | F9: =F8/126 -> 0.86777394 | G9: =G8/126 -> 0.88639485 | H9: =H8/126 -> 0.90371229 | I9: =I8/126 -> 0.91981751 | ... M9: =M8/126 -> 0.8969814
B10: 46023 | C10: 46054 | D10: 46082 | E10: 46113 | F10: 46143 | G10: 46174 | H10: 46204 | I10: 46235 | J10: 46266 | K10: 46296 | L10: 46327 | M10: 46357 | N10: Total
A11: Revenue Projection
A12: Rent Income | B12: =(16568/100)*B8*0.97 -> 16874.508 | C12: =(16568/100)*C8*0.97 -> 16978.969 | D12: =(16568/100)*D8*0.97 -> 17076.118 | E12: =(16568/100)*E8*0.97 -> 17166.467 | F12: =(16568/100)*F8*0.97 -> 17571.91 | G12: =(16568/100)*G8*0.97 -> 17948.972 | H12: =(16568/100)*H8*0.97 -> 18299.64 | I12: =(16568/100)*I8*0.97 -> 18625.761 | ... M12: =(16568/100)*M8*0.97 -> 18163.344 | N12: =SUM(B12:M12) -> 213559.16
A13: Other Rent Income | N13: =SUM(B13:M13) -> 0
A14: Other Rent Income | N14: =SUM(B14:M14) -> 0
A15: Total Rental Income | B15: =SUM(B12:B14) -> 16874.508 | C15: =SUM(C12:C14) -> 16978.969 | D15: =SUM(D12:D14) -> 17076.118 | E15: =SUM(E12:E14) -> 17166.467 | F15: =SUM(F12:F14) -> 17571.91 | G15: =SUM(G12:G14) -> 17948.972 | H15: =SUM(H12:H14) -> 18299.64 | I15: =SUM(I12:I14) -> 18625.761 | ... M15: =SUM(M12:M14) -> 18163.344 | N15: =(((((((((((B15)+(C15))+(D15))+(E15))+(F15))+(G15))+(H15))+(I15))+(J15))+(K15))+(L15))+(M15) -> 213559.16
A16: Fee Income
A17: Admin Fees | B17: =B6*20 -> 100 | C17: =C6*20 -> 160 | D17: =D6*20 -> 160 | E17: =E6*20 -> 160 | F17: =F6*20 -> 200 | G17: =G6*20 -> 200 | H17: =H6*20 -> 200 | I17: =I6*20 -> 200 | ... M17: =M6*20 -> 140 | N17: =SUM(B17:M17) -> 1940
A18: Late Fee Income | B18: =B12*0.03 -> 506.23524 | C18: =C12*0.03 -> 509.36908 | D18: =D12*0.03 -> 512.28355 | E18: =E12*0.03 -> 514.994 | F18: =F12*0.03 -> 527.1573 | G18: =G12*0.03 -> 538.46917 | H18: =H12*0.03 -> 548.98921 | I18: =I12*0.03 -> 558.77284 | ... M18: =M12*0.03 -> 544.90031 | N18: =SUM(B18:M18) -> 6406.7747
A19: Convenience Fee | B19: =5*(B8*0.05) -> 26.25 | C19: =5*(C8*0.05) -> 26.4125 | D19: =5*(D8*0.05) -> 26.563625 | E19: =5*(E8*0.05) -> 26.704171 | F19: =5*(F8*0.05) -> 27.334879 | G19: =5*(G8*0.05) -> 27.921438 | H19: =5*(H8*0.05) -> 28.466937 | I19: =5*(I8*0.05) -> 28.974251 | ... M19: =5*(M8*0.05) -> 28.254914 | N19: =SUM(B19:M19) -> 332.21282
A20: General Fee Income | N20: =SUM(B20:M20) -> 0
A21: Other Fee | N21: =SUM(B21:M21) -> 0
A22: Total Fee Income | B22: =SUM(B17:B21) -> 632.48524 | C22: =SUM(C17:C21) -> 695.78158 | D22: =SUM(D17:D21) -> 698.84717 | E22: =SUM(E17:E21) -> 701.69817 | F22: =SUM(F17:F21) -> 754.49218 | G22: =SUM(G17:G21) -> 766.39061 | H22: =SUM(H17:H21) -> 777.45615 | I22: =SUM(I17:I21) -> 787.7471 | ... M22: =SUM(M17:M21) -> 713.15522 | N22: =(((((((((((B22)+(C22))+(D22))+(E22))+(F22))+(G22))+(H22))+(I22))+(J22))+(K22))+(L22))+(M22) -> 8678.9875
A23: Ancillary Income
A24: Merchandise Income | B24: 0 | C24: 0 | D24: 0 | E24: 0 | F24: 0 | G24: 0 | H24: 0 | I24: 0 | J24: 0 | K24: 0 | L24: 0 | M24: 0 | N24: =SUM(B24:M24) -> 0
A25: Tenant Protection | B25: =B8*0.94*5 -> 493.5 | C25: =C8*0.94*5 -> 496.555 | D25: =D8*0.94*5 -> 499.39615 | E25: =E8*0.94*5 -> 502.03842 | F25: =F8*0.94*5 -> 513.89573 | G25: =G8*0.94*5 -> 524.92303 | H25: =H8*0.94*5 -> 535.17842 | I25: =I8*0.94*5 -> 544.71593 | ... M25: =M8*0.94*5 -> 531.19238 | N25: =SUM(B25:M25) -> 6245.601
A26: Truck Rentals | N26: =SUM(B26:M26) -> 0
A27: Propane Sales | N27: =SUM(B27:M27) -> 0
A28: Other Income Sources | N28: =SUM(B28:M28) -> 0
A29: Other Income Sources | N29: =SUM(B29:M29) -> 0
A30: Total Ancillary Income | B30: =SUM(B24:B29) -> 493.5 | C30: =SUM(C24:C29) -> 496.555 | D30: =SUM(D24:D29) -> 499.39615 | E30: =SUM(E24:E29) -> 502.03842 | F30: =SUM(F24:F29) -> 513.89573 | G30: =SUM(G24:G29) -> 524.92303 | H30: =SUM(H24:H29) -> 535.17842 | I30: =SUM(I24:I29) -> 544.71593 | ... M30: =SUM(M24:M29) -> 531.19238 | N30: =(((((((((((B30)+(C30))+(D30))+(E30))+(F30))+(G30))+(H30))+(I30))+(J30))+(K30))+(L30))+(M30) -> 6245.601
A31: Total Revenue | B31: =B15+B22+B30 -> 18000.493 | C31: =C15+C22+C30 -> 18171.306 | D31: =D15+D22+D30 -> 18274.362 | E31: =E15+E22+E30 -> 18370.203 | F31: =F15+F22+F30 -> 18840.298 | G31: =G15+G22+G30 -> 19240.286 | H31: =H15+H22+H30 -> 19612.275 | I31: =I15+I22+I30 -> 19958.224 | ... M31: =M15+M22+M30 -> 19407.691 | N31: =SUM(B31:M31) -> 228483.74
A33: Expense Projection
A34: Advertising/Marketing
A35: PPC (payperclick) | B35: 300 | C35: =B35 -> 300 | D35: =C35 -> 300 | E35: =D35 -> 300 | F35: =E35 -> 300 | G35: =F35 -> 300 | H35: =G35 -> 300 | I35: =H35 -> 300 | J35: =I35 -> 300 | ... M35: =L35 -> 300 | N35: =(((((((((((B35)+(C35))+(D35))+(E35))+(F35))+(G35))+(H35))+(I35))+(J35))+(K35))+(L35))+(M35) -> 3600
A36: Print Materials | B36: 0 | C36: 0 | D36: 100 | E36: 0 | F36: =0 -> 0 | G36: =0 -> 0 | H36: 100 | I36: =0 -> 0 | J36: =0 -> 0 | K36: =0 -> 0 | L36: 100 | M36: =0 -> 0 | N36: =(((((((((((B36)+(C36))+(D36))+(E36))+(F36))+(G36))+(H36))+(I36))+(J36))+(K36))+(L36))+(M36) -> 300
A37: Reputation & Social | B37: 0 | C37: =B37 -> 0 | D37: =C37 -> 0 | E37: =D37 -> 0 | F37: =E37 -> 0 | G37: =F37 -> 0 | H37: =G37 -> 0 | I37: =H37 -> 0 | J37: =I37 -> 0 | ... M37: =L37 -> 0 | N37: =(((((((((((B37)+(C37))+(D37))+(E37))+(F37))+(G37))+(H37))+(I37))+(J37))+(K37))+(L37))+(M37) -> 0
A38: Website | B38: 300 | C38: =B38 -> 300 | D38: =C38 -> 300 | E38: =D38 -> 300 | F38: =E38 -> 300 | G38: =F38 -> 300 | H38: =G38 -> 300 | I38: =H38 -> 300 | J38: =I38 -> 300 | ... M38: =L38 -> 300 | N38: =(((((((((((B38)+(C38))+(D38))+(E38))+(F38))+(G38))+(H38))+(I38))+(J38))+(K38))+(L38))+(M38) -> 3600
A39: Sparefoot | B39: 0 | C39: =B39 -> 0 | D39: =C39 -> 0 | E39: =D39 -> 0 | F39: =E39 -> 0 | G39: =F39 -> 0 | H39: =G39 -> 0 | I39: =H39 -> 0 | J39: =I39 -> 0 | ... M39: =L39 -> 0 | N39: =(((((((((((B39)+(C39))+(D39))+(E39))+(F39))+(G39))+(H39))+(I39))+(J39))+(K39))+(L39))+(M39) -> 0
A40: Advertising/Marketing | B40: =SUM(B35:B39) -> 600 | C40: =SUM(C35:C39) -> 600 | D40: =SUM(D35:D39) -> 700 | E40: =SUM(E35:E39) -> 600 | F40: =SUM(F35:F39) -> 600 | G40: =SUM(G35:G39) -> 600 | H40: =SUM(H35:H39) -> 700 | I40: =SUM(I35:I39) -> 600 | ... M40: =SUM(M35:M39) -> 600 | N40: =(((((((((((B40)+(C40))+(D40))+(E40))+(F40))+(G40))+(H40))+(I40))+(J40))+(K40))+(L40))+(M40) -> 7500
A41: Legal & Professional Fees | N41: =(((((((((((B41)+(C41))+(D41))+(E41))+(F41))+(G41))+(H41))+(I41))+(J41))+(K41))+(L41))+(M41) -> 0
A42: Auction Expenses | B42: 100 | C42: 100 | D42: 100 | E42: 100 | F42: 100 | G42: 100 | H42: 100 | I42: 100 | J42: 100 | K42: 100 | L42: 100 | M42: 100 | N42: =(((((((((((B42)+(C42))+(D42))+(E42))+(F42))+(G42))+(H42))+(I42))+(J42))+(K42))+(L42))+(M42) -> 1200
A43: Management Services | B43: =IF(B31*0.06<1000,1000,B31*0.06) -> 1080.0296 | C43: =IF(C31*0.06<1000,1000,C31*0.06) -> 1090.2783 | D43: =IF(D31*0.06<1000,1000,D31*0.06) -> 1096.4617 | E43: =IF(E31*0.06<1000,1000,E31*0.06) -> 1102.2122 | F43: =IF(F31*0.06<1000,1000,F31*0.06) -> 1130.4179 | G43: =IF(G31*0.06<1000,1000,G31*0.06) -> 1154.4172 | H43: =IF(H31*0.06<1000,1000,H31*0.06) -> 1176.7365 | I43: =IF(I31*0.06<1000,1000,I31*0.06) -> 1197.4935 | ... M43: =IF(M31*0.06<1000,1000,M31*0.06) -> 1164.4615 | N43: =(((((((((((B43)+(C43))+(D43))+(E43))+(F43))+(G43))+(H43))+(I43))+(J43))+(K43))+(L43))+(M43) -> 13709.025
A44: Call Center | B44: 0 | C44: 0 | D44: 0 | E44: 0 | F44: 0 | G44: 0 | H44: 0 | I44: 0 | J44: 0 | K44: 0 | L44: 0 | M44: 0 | N44: =(((((((((((B44)+(C44))+(D44))+(E44))+(F44))+(G44))+(H44))+(I44))+(J44))+(K44))+(L44))+(M44) -> 0
A45: Legal Fees | B45: 0 | C45: 0 | D45: 0 | E45: 0 | F45: 0 | G45: 0 | H45: 150 | I45: 75 | J45: 0 | K45: 0 | L45: 0 | M45: 0 | N45: =(((((((((((B45)+(C45))+(D45))+(E45))+(F45))+(G45))+(H45))+(I45))+(J45))+(K45))+(L45))+(M45) -> 225
A46: Accounting Fees | B46: 0 | C46: 0 | D46: 0 | E46: 0 | F46: 0 | G46: 0 | H46: 150 | I46: 0 | J46: 0 | K46: 0 | L46: 0 | M46: 0 | N46: =(((((((((((B46)+(C46))+(D46))+(E46))+(F46))+(G46))+(H46))+(I46))+(J46))+(K46))+(L46))+(M46) -> 150
A47: Total Legal & Professional Fees | B47: =SUM(B42:B46) -> 1180.0296 | C47: =SUM(C42:C46) -> 1190.2783 | D47: =SUM(D42:D46) -> 1196.4617 | E47: =SUM(E42:E46) -> 1202.2122 | F47: =SUM(F42:F46) -> 1230.4179 | G47: =SUM(G42:G46) -> 1254.4172 | H47: =SUM(H42:H46) -> 1576.7365 | I47: =SUM(I42:I46) -> 1372.4935 | ... M47: =SUM(M42:M46) -> 1264.4615 | N47: =(((((((((((B47)+(C47))+(D47))+(E47))+(F47))+(G47))+(H47))+(I47))+(J47))+(K47))+(L47))+(M47) -> 15284.025
A48: Office/Site
A49: Cost of Merchandise Sold | B49: =B24*0.4 -> 0 | C49: =C24*0.4 -> 0 | D49: =D24*0.4 -> 0 | E49: =E24*0.4 -> 0 | F49: =F24*0.4 -> 0 | G49: =G24*0.4 -> 0 | H49: =H24*0.4 -> 0 | I49: =I24*0.4 -> 0 | ... M49: =M24*0.4 -> 0 | N49: =(((((((((((B49)+(C49))+(D49))+(E49))+(F49))+(G49))+(H49))+(I49))+(J49))+(K49))+(L49))+(M49) -> 0
A50: Site Supplies | B50: 50 | C50: 50 | D50: 50 | E50: 50 | F50: 50 | G50: 50 | H50: 50 | I50: 50 | J50: 50 | K50: 50 | L50: 50 | M50: 50 | N50: =(((((((((((B50)+(C50))+(D50))+(E50))+(F50))+(G50))+(H50))+(I50))+(J50))+(K50))+(L50))+(M50) -> 600
A51: Office Supplies | B51: 50 | C51: 50 | D51: 50 | E51: 50 | F51: 50 | G51: 50 | H51: 50 | I51: 50 | J51: 50 | K51: 50 | L51: 50 | M51: 50 | N51: =(((((((((((B51)+(C51))+(D51))+(E51))+(F51))+(G51))+(H51))+(I51))+(J51))+(K51))+(L51))+(M51) -> 600
A52: Business Licenses
A53: Site Supplies
A54: Office Supplies
A55: Total Office/Site | B55: =SUM(B49:B54) -> 100 | C55: =SUM(C49:C54) -> 100 | D55: =SUM(D49:D54) -> 100 | E55: =SUM(E49:E54) -> 100 | F55: =SUM(F49:F54) -> 100 | G55: =SUM(G49:G54) -> 100 | H55: =SUM(H49:H54) -> 100 | I55: =SUM(I49:I54) -> 100 | ... M55: =SUM(M49:M54) -> 100 | N55: =(((((((((((B55)+(C55))+(D55))+(E55))+(F55))+(G55))+(H55))+(I55))+(J55))+(K55))+(L55))+(M55) -> 1200
A56: Repairs and Maintenance
A57: Lawn/Snow | B57: 300 | C57: 300 | D57: 300 | E57: 300 | F57: 300 | G57: 300 | H57: 300 | I57: 300 | J57: 300 | K57: 300 | L57: 300 | M57: 300 | N57: =(((((((((((B57)+(C57))+(D57))+(E57))+(F57))+(G57))+(H57))+(I57))+(J57))+(K57))+(L57))+(M57) -> 3600
A58: Elevator | N58: =(((((((((((B58)+(C58))+(D58))+(E58))+(F58))+(G58))+(H58))+(I58))+(J58))+(K58))+(L58))+(M58) -> 0
A59: Gate & Fence
A60: Unit Doors
A61: Security System
A62: HVAC
A63: Pest Control | N63: =(((((((((((B63)+(C63))+(D63))+(E63))+(F63))+(G63))+(H63))+(I63))+(J63))+(K63))+(L63))+(M63) -> 0
A64: Site | B64: 300 | C64: 300 | D64: 300 | E64: 300 | F64: 300 | G64: 300 | H64: 300 | I64: 300 | J64: 300 | K64: 300 | L64: 300 | M64: 300 | N64: =(((((((((((B64)+(C64))+(D64))+(E64))+(F64))+(G64))+(H64))+(I64))+(J64))+(K64))+(L64))+(M64) -> 3600
A65: Trash Hauling
A66: Total Repairs and Maintenance | B66: =SUM(B57:B65) -> 600 | C66: =SUM(C57:C65) -> 600 | D66: =SUM(D57:D65) -> 600 | E66: =SUM(E57:E65) -> 600 | F66: =SUM(F57:F65) -> 600 | G66: =SUM(G57:G65) -> 600 | H66: =SUM(H57:H65) -> 600 | I66: =SUM(I57:I65) -> 600 | ... M66: =SUM(M57:M65) -> 600 | N66: =(((((((((((B66)+(C66))+(D66))+(E66))+(F66))+(G66))+(H66))+(I66))+(J66))+(K66))+(L66))+(M66) -> 7200
A67: Service Charges
A68: Bank Service Charges | B68: 0 | C68: =B68 -> 0 | D68: =C68 -> 0 | E68: =D68 -> 0 | F68: =E68 -> 0 | G68: =F68 -> 0 | H68: =G68 -> 0 | I68: =H68 -> 0 | J68: =I68 -> 0 | ... M68: =L68 -> 0 | N68: =(((((((((((B68)+(C68))+(D68))+(E68))+(F68))+(G68))+(H68))+(I68))+(J68))+(K68))+(L68))+(M68) -> 0
A69: Credit Card Service Fees | B69: =B31*0.027 -> 486.01332 | C69: =C31*0.027 -> 490.62526 | D69: =D31*0.027 -> 493.40776 | E69: =E31*0.027 -> 495.99549 | F69: =F31*0.027 -> 508.68804 | G69: =G31*0.027 -> 519.48772 | H69: =H31*0.027 -> 529.53142 | I69: =I31*0.027 -> 538.87206 | ... M69: =M31*0.027 -> 524.00767 | N69: =N31*0.02 -> 4569.6749
A70: Total Service Charges | B70: =SUM(B68:B69) -> 486.01332 | C70: =SUM(C68:C69) -> 490.62526 | D70: =SUM(D68:D69) -> 493.40776 | E70: =SUM(E68:E69) -> 495.99549 | F70: =SUM(F68:F69) -> 508.68804 | G70: =SUM(G68:G69) -> 519.48772 | H70: =SUM(H68:H69) -> 529.53142 | I70: =SUM(I68:I69) -> 538.87206 | ... M70: =SUM(M68:M69) -> 524.00767 | N70: =(((((((((((B70)+(C70))+(D70))+(E70))+(F70))+(G70))+(H70))+(I70))+(J70))+(K70))+(L70))+(M70) -> 6169.0611
A71: Software
A72: Gate Software | B72: 90 | C72: 90 | D72: 90 | E72: 90 | F72: 90 | G72: 90 | H72: 90 | I72: 90 | J72: 90 | K72: 90 | L72: 90 | M72: 90 | N72: =(((((((((((B72)+(C72))+(D72))+(E72))+(F72))+(G72))+(H72))+(I72))+(J72))+(K72))+(L72))+(M72) -> 1080
A73: Collection Software | N73: =(((((((((((B73)+(C73))+(D73))+(E73))+(F73))+(G73))+(H73))+(I73))+(J73))+(K73))+(L73))+(M73) -> 0
A74: Accounting/BillPay Software | B74: 80 | C74: 80 | D74: 80 | E74: 80 | F74: 80 | G74: 80 | H74: 80 | I74: 80 | J74: 80 | K74: 80 | L74: 80 | M74: 80 | N74: =(((((((((((B74)+(C74))+(D74))+(E74))+(F74))+(G74))+(H74))+(I74))+(J74))+(K74))+(L74))+(M74) -> 960
A75: Other Software (Swivel) | B75: 63 | C75: 63 | D75: 63 | E75: 63 | F75: 63 | G75: 63 | H75: 63 | I75: 63 | J75: 63 | K75: 63 | L75: 63 | M75: 63 | N75: =(((((((((((B75)+(C75))+(D75))+(E75))+(F75))+(G75))+(H75))+(I75))+(J75))+(K75))+(L75))+(M75) -> 756
A76: Storage Software | B76: 145 | C76: =B76 -> 145 | D76: =C76 -> 145 | E76: =D76 -> 145 | F76: =E76 -> 145 | G76: =F76 -> 145 | H76: =G76 -> 145 | I76: =H76 -> 145 | J76: =I76 -> 145 | ... M76: =L76 -> 145 | N76: =(((((((((((B76)+(C76))+(D76))+(E76))+(F76))+(G76))+(H76))+(I76))+(J76))+(K76))+(L76))+(M76) -> 1740
A77: Total Software | B77: =SUM(B72:B76) -> 378 | C77: =SUM(C72:C76) -> 378 | D77: =SUM(D72:D76) -> 378 | E77: =SUM(E72:E76) -> 378 | F77: =SUM(F72:F76) -> 378 | G77: =SUM(G72:G76) -> 378 | H77: =SUM(H72:H76) -> 378 | I77: =SUM(I72:I76) -> 378 | ... M77: =SUM(M72:M76) -> 378 | N77: =(((((((((((B77)+(C77))+(D77))+(E77))+(F77))+(G77))+(H77))+(I77))+(J77))+(K77))+(L77))+(M77) -> 4536
A78: Staffing
A79: Mileage | N79: =(((((((((((B79)+(C79))+(D79))+(E79))+(F79))+(G79))+(H79))+(I79))+(J79))+(K79))+(L79))+(M79) -> 0
A80: Payroll Processing | N80: =(((((((((((B80)+(C80))+(D80))+(E80))+(F80))+(G80))+(H80))+(I80))+(J80))+(K80))+(L80))+(M80) -> 0
A81: Payroll Taxes | N81: =(((((((((((B81)+(C81))+(D81))+(E81))+(F81))+(G81))+(H81))+(I81))+(J81))+(K81))+(L81))+(M81) -> 0
A82: Staff Costs | N82: =(((((((((((B82)+(C82))+(D82))+(E82))+(F82))+(G82))+(H82))+(I82))+(J82))+(K82))+(L82))+(M82) -> 0
A83: Health Insurance | N83: =(((((((((((B83)+(C83))+(D83))+(E83))+(F83))+(G83))+(H83))+(I83))+(J83))+(K83))+(L83))+(M83) -> 0
A84: Salary/Wages | B84: 600 | C84: =B84 -> 600 | D84: =C84 -> 600 | E84: =D84 -> 600 | F84: =E84 -> 600 | G84: =F84 -> 600 | H84: =G84 -> 600 | I84: =H84 -> 600 | J84: =I84 -> 600 | ... M84: =L84 -> 600 | N84: =(((((((((((B84)+(C84))+(D84))+(E84))+(F84))+(G84))+(H84))+(I84))+(J84))+(K84))+(L84))+(M84) -> 7200
A85: Workers Comp | N85: =(((((((((((B85)+(C85))+(D85))+(E85))+(F85))+(G85))+(H85))+(I85))+(J85))+(K85))+(L85))+(M85) -> 0
A86: Total Staffing | B86: =SUM(B79:B85) -> 600 | C86: =SUM(C79:C85) -> 600 | D86: =SUM(D79:D85) -> 600 | E86: =SUM(E79:E85) -> 600 | F86: =SUM(F79:F85) -> 600 | G86: =SUM(G79:G85) -> 600 | H86: =SUM(H79:H85) -> 600 | I86: =SUM(I79:I85) -> 600 | ... M86: =SUM(M79:M85) -> 600 | N86: =(((((((((((B86)+(C86))+(D86))+(E86))+(F86))+(G86))+(H86))+(I86))+(J86))+(K86))+(L86))+(M86) -> 7200
A87: Taxes & Insurance
A88: Insurance - Prop & GL | B88: 1300.97 | C88: 1300.97 | D88: 1300.97 | E88: 1300.97 | F88: 1300.97 | G88: 1300.97 | H88: 1300.97 | I88: 1300.97 | J88: 1300.97 | K88: 1300.97 | L88: 1300.97 | M88: 1300.97 | N88: =(((((((((((B88)+(C88))+(D88))+(E88))+(F88))+(G88))+(H88))+(I88))+(J88))+(K88))+(L88))+(M88) -> 15611.64
A89: Taxes-Property | B89: =3728.73/2 -> 1864.365 | C89: =3728.73/2 -> 1864.365 | D89: =3728.73/2 -> 1864.365 | E89: =3728.73/2 -> 1864.365 | F89: =3728.73/2 -> 1864.365 | G89: =3728.73/2 -> 1864.365 | H89: =3728.73/2 -> 1864.365 | I89: =3728.73/2 -> 1864.365 | ... M89: =3728.73/2 -> 1864.365 | N89: =(((((((((((B89)+(C89))+(D89))+(E89))+(F89))+(G89))+(H89))+(I89))+(J89))+(K89))+(L89))+(M89) -> 22372.38
A90: Total Taxes & Insurance | B90: =SUM(B88:B89) -> 3165.335 | C90: =SUM(C88:C89) -> 3165.335 | D90: =SUM(D88:D89) -> 3165.335 | E90: =SUM(E88:E89) -> 3165.335 | F90: =SUM(F88:F89) -> 3165.335 | G90: =SUM(G88:G89) -> 3165.335 | H90: =SUM(H88:H89) -> 3165.335 | I90: =SUM(I88:I89) -> 3165.335 | ... M90: =SUM(M88:M89) -> 3165.335 | N90: =(((((((((((B90)+(C90))+(D90))+(E90))+(F90))+(G90))+(H90))+(I90))+(J90))+(K90))+(L90))+(M90) -> 37984.02
A91: Utilities
A92: Telephone | B92: 40 | C92: 40 | D92: 40 | E92: 40 | F92: 40 | G92: 40 | H92: 40 | I92: 40 | J92: 40 | K92: 40 | L92: 40 | M92: 40 | N92: =(((((((((((B92)+(C92))+(D92))+(E92))+(F92))+(G92))+(H92))+(I92))+(J92))+(K92))+(L92))+(M92) -> 480
A93: Internet | B93: 100 | C93: 100 | D93: 100 | E93: 100 | F93: 100 | G93: 100 | H93: 100 | I93: 100 | J93: 100 | K93: 100 | L93: 100 | M93: 100 | N93: =(((((((((((B93)+(C93))+(D93))+(E93))+(F93))+(G93))+(H93))+(I93))+(J93))+(K93))+(L93))+(M93) -> 1200
A94: Electricity | B94: 230 | C94: 230 | D94: 230 | E94: 230 | F94: 230 | G94: 230 | H94: 230 | I94: 230 | J94: 230 | K94: 230 | L94: 230 | M94: 230 | N94: =(((((((((((B94)+(C94))+(D94))+(E94))+(F94))+(G94))+(H94))+(I94))+(J94))+(K94))+(L94))+(M94) -> 2760
A95: Water & Sewer | B95: 200 | C95: 200 | D95: 200 | E95: 200 | F95: 200 | G95: 200 | H95: 200 | I95: 200 | J95: 200 | K95: 200 | L95: 200 | M95: 200 | N95: =(((((((((((B95)+(C95))+(D95))+(E95))+(F95))+(G95))+(H95))+(I95))+(J95))+(K95))+(L95))+(M95) -> 2400
A96: Gas | N96: =(((((((((((B96)+(C96))+(D96))+(E96))+(F96))+(G96))+(H96))+(I96))+(J96))+(K96))+(L96))+(M96) -> 0
A97: Stormwater | N97: =(((((((((((B97)+(C97))+(D97))+(E97))+(F97))+(G97))+(H97))+(I97))+(J97))+(K97))+(L97))+(M97) -> 0
A98: Trash/Disposal | N98: =(((((((((((B98)+(C98))+(D98))+(E98))+(F98))+(G98))+(H98))+(I98))+(J98))+(K98))+(L98))+(M98) -> 0
A99: Total Utilities | B99: =SUM(B92:B98) -> 570 | C99: =SUM(C92:C98) -> 570 | D99: =SUM(D92:D98) -> 570 | E99: =SUM(E92:E98) -> 570 | F99: =SUM(F92:F98) -> 570 | G99: =SUM(G92:G98) -> 570 | H99: =SUM(H92:H98) -> 570 | I99: =SUM(I92:I98) -> 570 | ... M99: =SUM(M92:M98) -> 570 | N99: =(((((((((((B99)+(C99))+(D99))+(E99))+(F99))+(G99))+(H99))+(I99))+(J99))+(K99))+(L99))+(M99) -> 6840
A100: Total Expenses | B100: =B40+B47+B55+B66+B70+B77+B86+B90+B99 -> 7679.3779 | C100: =C40+C47+C55+C66+C70+C77+C86+C90+C99 -> 7694.2386 | D100: =D40+D47+D55+D66+D70+D77+D86+D90+D99 -> 7803.2045 | E100: =E40+E47+E55+E66+E70+E77+E86+E90+E99 -> 7711.5427 | F100: =F40+F47+F55+F66+F70+F77+F86+F90+F99 -> 7752.4409 | G100: =G40+G47+G55+G66+G70+G77+G86+G90+G99 -> 7787.2399 | H100: =H40+H47+H55+H66+H70+H77+H86+H90+H99 -> 8219.6029 | I100: =I40+I47+I55+I66+I70+I77+I86+I90+I99 -> 7924.7005 | ... M100: =M40+M47+M55+M66+M70+M77+M86+M90+M99 -> 7801.8041 | N100: =(((((((((((B100)+(C100))+(D100))+(E100))+(F100))+(G100))+(H100))+(I100))+(J100))+(K100))+(L100))+(M100) -> 93913.106
A101: Net Operating Income | B101: =B31-B100 -> 10321.115 | C101: =C31-C100 -> 10477.067 | D101: =D31-D100 -> 10471.157 | E101: =E31-E100 -> 10658.661 | F101: =F31-F100 -> 11087.857 | G101: =G31-G100 -> 11453.046 | H101: =H31-H100 -> 11392.672 | I101: =I31-I100 -> 12033.524 | ... M101: =M31-M100 -> 11605.887 | N101: =(((((((((((B101)+(C101))+(D101))+(E101))+(F101))+(G101))+(H101))+(I101))+(J101))+(K101))+(L101))+(M101) -> 134570.64
A103: Other Income/Expenses
...
